{"v":"5.7.1","fr":29.9700012207031,"ip":0,"op":430.000017514259,"w":1080,"h":1080,"nm":"Main","ddd":0,"assets":[],"layers":[{"ddd":0,"ind":1,"ty":3,"nm":"Null 4","sr":1,"ks":{"o":{"a":0,"k":0,"ix":11},"r":{"a":0,"k":0,"ix":10},"p":{"a":0,"k":[540,540,0],"ix":2},"a":{"a":0,"k":[0,0,0],"ix":1},"s":{"a":1,"k":[{"i":{"x":[0.833,0.833,0.833],"y":[0.833,0.833,0.833]},"o":{"x":[0.167,0.167,0.167],"y":[0.167,0.167,0.167]},"t":45,"s":[100,100,100]},{"t":50.0000020365418,"s":[128,128,100]}],"ix":6}},"ao":0,"ip":0,"op":430.000017514259,"st":0,"bm":0},{"ddd":0,"ind":2,"ty":4,"nm":"tip 7","parent":1,"sr":1,"ks":{"o":{"a":1,"k":[{"i":{"x":[0.833],"y":[0.833]},"o":{"x":[0.167],"y":[0.167]},"t":420,"s":[100]},{"t":423.000017229143,"s":[0]}],"ix":11},"r":{"a":0,"k":49.544,"ix":10},"p":{"a":1,"k":[{"i":{"x":0.833,"y":0.833},"o":{"x":0.167,"y":0.167},"t":76,"s":[-291,-31.75,0],"to":[0,0,0],"ti":[0,0,0]},{"t":95.0000038694293,"s":[-290,-210,0]}],"ix":2},"a":{"a":0,"k":[-280.5,-20,0],"ix":1},"s":{"a":0,"k":[100,100,100],"ix":6}},"ao":0,"shapes":[{"ty":"gr","it":[{"ind":0,"ty":"sh","ix":1,"ks":{"a":0,"k":{"i":[[0,0],[0,0],[0,0]],"o":[[0,0],[0,0],[0,0]],"v":[[-295,-33],[-289.5,-8.5],[-271,-30]],"c":true},"ix":2},"nm":"Path 1","mn":"ADBE Vector Shape - Group","hd":false},{"ty":"fl","c":{"a":0,"k":[0.992156922583,0.403921598547,0.090196078431,1],"ix":4},"o":{"a":0,"k":100,"ix":5},"r":1,"bm":0,"nm":"Fill 1","mn":"ADBE Vector Graphic - Fill","hd":false},{"ty":"tr","p":{"a":0,"k":[0,0],"ix":2},"a":{"a":0,"k":[0,0],"ix":1},"s":{"a":0,"k":[100,100],"ix":3},"r":{"a":0,"k":0,"ix":6},"o":{"a":0,"k":100,"ix":7},"sk":{"a":0,"k":0,"ix":4},"sa":{"a":0,"k":0,"ix":5},"nm":"Transform"}],"nm":"Shape 1","np":3,"cix":2,"bm":0,"ix":1,"mn":"ADBE Vector Group","hd":false}],"ip":76.0000030955435,"op":428.000017432797,"st":0,"bm":0},{"ddd":0,"ind":3,"ty":4,"nm":"arrow 4","parent":1,"sr":1,"ks":{"o":{"a":1,"k":[{"i":{"x":[0.833],"y":[0.833]},"o":{"x":[0.167],"y":[0.167]},"t":420,"s":[100]},{"t":423.000017229143,"s":[0]}],"ix":11},"r":{"a":0,"k":0,"ix":10},"p":{"a":0,"k":[-290.5,-30.25,0],"ix":2},"a":{"a":0,"k":[-66,165.25,0],"ix":1},"s":{"a":0,"k":[100,100,100],"ix":6}},"ao":0,"shapes":[{"ty":"gr","it":[{"ind":0,"ty":"sh","ix":1,"ks":{"a":0,"k":{"i":[[0,0],[0,0]],"o":[[0,0],[0,0]],"v":[[-66,165],[-65.5,-19.5]],"c":false},"ix":2},"nm":"Path 1","mn":"ADBE Vector Shape - Group","hd":false},{"ty":"st","c":{"a":0,"k":[0.990716911765,0.402096677294,0.089480186911,1],"ix":3},"o":{"a":0,"k":100,"ix":4},"w":{"a":0,"k":6,"ix":5},"lc":1,"lj":1,"ml":4,"bm":0,"nm":"Stroke 1","mn":"ADBE Vector Graphic - Stroke","hd":false},{"ty":"fl","c":{"a":0,"k":[0.678431372549,0.129411764706,0.792156922583,1],"ix":4},"o":{"a":0,"k":100,"ix":5},"r":1,"bm":0,"nm":"Fill 1","mn":"ADBE Vector Graphic - Fill","hd":false},{"ty":"tr","p":{"a":0,"k":[0,0],"ix":2},"a":{"a":0,"k":[0,0],"ix":1},"s":{"a":0,"k":[100,100],"ix":3},"r":{"a":0,"k":0,"ix":6},"o":{"a":0,"k":100,"ix":7},"sk":{"a":0,"k":0,"ix":4},"sa":{"a":0,"k":0,"ix":5},"nm":"Transform"}],"nm":"Shape 1","np":3,"cix":2,"bm":0,"ix":1,"mn":"ADBE Vector Group","hd":false},{"ty":"tm","s":{"a":1,"k":[{"i":{"x":[0.833],"y":[0.833]},"o":{"x":[0.167],"y":[0.167]},"t":76,"s":[0]},{"t":95.0000038694293,"s":[0]}],"ix":1},"e":{"a":1,"k":[{"i":{"x":[0.833],"y":[0.833]},"o":{"x":[0.167],"y":[0.167]},"t":76,"s":[0]},{"t":95.0000038694293,"s":[100]}],"ix":2},"o":{"a":0,"k":0,"ix":3},"m":1,"ix":2,"nm":"Trim Paths 1","mn":"ADBE Vector Filter - Trim","hd":false}],"ip":47.0000019143492,"op":428.000017432797,"st":0,"bm":0},{"ddd":0,"ind":4,"ty":4,"nm":"v arrow 2","parent":1,"sr":1,"ks":{"o":{"a":1,"k":[{"i":{"x":[0.833],"y":[0.833]},"o":{"x":[0.167],"y":[0.167]},"t":71,"s":[0]},{"i":{"x":[0.833],"y":[0.833]},"o":{"x":[0.167],"y":[0.167]},"t":74,"s":[100]},{"i":{"x":[0.833],"y":[0.833]},"o":{"x":[0.167],"y":[0.167]},"t":420,"s":[100]},{"t":423.000017229143,"s":[0]}],"ix":11},"r":{"a":0,"k":0,"ix":10},"p":{"a":0,"k":[-204.5,71.5,0],"ix":2},"a":{"a":0,"k":[-185,-171.5,0],"ix":1},"s":{"a":0,"k":[100,100,100],"ix":6}},"ao":0,"shapes":[{"ty":"gr","it":[{"ind":0,"ty":"sh","ix":1,"ks":{"a":0,"k":{"i":[[0,0],[0,0],[0,0]],"o":[[0,0],[0,0],[0,0]],"v":[[-176.5,-175.75],[-176.5,-167.25],[-169.5,-171.25]],"c":true},"ix":2},"nm":"Path 1","mn":"ADBE Vector Shape - Group","hd":false},{"ty":"fl","c":{"a":0,"k":[0.129411764706,0.792156922583,0.658823529412,1],"ix":4},"o":{"a":0,"k":100,"ix":5},"r":1,"bm":0,"nm":"Fill 1","mn":"ADBE Vector Graphic - Fill","hd":false},{"ty":"tr","p":{"a":0,"k":[0,0],"ix":2},"a":{"a":0,"k":[0,0],"ix":1},"s":{"a":0,"k":[100,100],"ix":3},"r":{"a":0,"k":0,"ix":6},"o":{"a":0,"k":100,"ix":7},"sk":{"a":0,"k":0,"ix":4},"sa":{"a":0,"k":0,"ix":5},"nm":"Transform"}],"nm":"Shape 2","np":3,"cix":2,"bm":0,"ix":1,"mn":"ADBE Vector Group","hd":false},{"ty":"gr","it":[{"ind":0,"ty":"sh","ix":1,"ks":{"a":0,"k":{"i":[[0,0],[0,0]],"o":[[0,0],[0,0]],"v":[[-200.5,-171.5],[-173,-171.5]],"c":false},"ix":2},"nm":"Path 1","mn":"ADBE Vector Shape - Group","hd":false},{"ty":"st","c":{"a":0,"k":[0.129411764706,0.792156922583,0.658823529412,1],"ix":3},"o":{"a":0,"k":100,"ix":4},"w":{"a":0,"k":3,"ix":5},"lc":1,"lj":1,"ml":4,"bm":0,"nm":"Stroke 1","mn":"ADBE Vector Graphic - Stroke","hd":false},{"ty":"fl","c":{"a":0,"k":[0.992156922583,0.403921598547,0.090196078431,1],"ix":4},"o":{"a":0,"k":100,"ix":5},"r":1,"bm":0,"nm":"Fill 1","mn":"ADBE Vector Graphic - Fill","hd":false},{"ty":"tr","p":{"a":0,"k":[0,0],"ix":2},"a":{"a":0,"k":[0,0],"ix":1},"s":{"a":0,"k":[100,100],"ix":3},"r":{"a":0,"k":0,"ix":6},"o":{"a":0,"k":100,"ix":7},"sk":{"a":0,"k":0,"ix":4},"sa":{"a":0,"k":0,"ix":5},"nm":"Transform"}],"nm":"Shape 1","np":3,"cix":2,"bm":0,"ix":2,"mn":"ADBE Vector Group","hd":false}],"ip":65.0000026475043,"op":428.000017432797,"st":0,"bm":0},{"ddd":0,"ind":5,"ty":4,"nm":"v arrow","parent":1,"sr":1,"ks":{"o":{"a":1,"k":[{"i":{"x":[0.833],"y":[0.833]},"o":{"x":[0.167],"y":[0.167]},"t":92,"s":[0]},{"i":{"x":[0.833],"y":[0.833]},"o":{"x":[0.167],"y":[0.167]},"t":95,"s":[100]},{"i":{"x":[0.833],"y":[0.833]},"o":{"x":[0.167],"y":[0.167]},"t":420,"s":[100]},{"t":423.000017229143,"s":[0]}],"ix":11},"r":{"a":0,"k":0,"ix":10},"p":{"a":0,"k":[-144.375,-123.063,0],"ix":2},"a":{"a":0,"k":[-185,-171.5,0],"ix":1},"s":{"a":0,"k":[100,100,100],"ix":6}},"ao":0,"shapes":[{"ty":"gr","it":[{"ind":0,"ty":"sh","ix":1,"ks":{"a":0,"k":{"i":[[0,0],[0,0],[0,0]],"o":[[0,0],[0,0],[0,0]],"v":[[-176.5,-175.75],[-176.5,-167.25],[-169.5,-171.25]],"c":true},"ix":2},"nm":"Path 1","mn":"ADBE Vector Shape - Group","hd":false},{"ty":"fl","c":{"a":0,"k":[0.129411764706,0.792156922583,0.658823529412,1],"ix":4},"o":{"a":0,"k":100,"ix":5},"r":1,"bm":0,"nm":"Fill 1","mn":"ADBE Vector Graphic - Fill","hd":false},{"ty":"tr","p":{"a":0,"k":[0,0],"ix":2},"a":{"a":0,"k":[0,0],"ix":1},"s":{"a":0,"k":[100,100],"ix":3},"r":{"a":0,"k":0,"ix":6},"o":{"a":0,"k":100,"ix":7},"sk":{"a":0,"k":0,"ix":4},"sa":{"a":0,"k":0,"ix":5},"nm":"Transform"}],"nm":"Shape 2","np":3,"cix":2,"bm":0,"ix":1,"mn":"ADBE Vector Group","hd":false},{"ty":"gr","it":[{"ind":0,"ty":"sh","ix":1,"ks":{"a":0,"k":{"i":[[0,0],[0,0]],"o":[[0,0],[0,0]],"v":[[-200.5,-171.5],[-173,-171.5]],"c":false},"ix":2},"nm":"Path 1","mn":"ADBE Vector Shape - Group","hd":false},{"ty":"st","c":{"a":0,"k":[0.129411764706,0.792156922583,0.658823529412,1],"ix":3},"o":{"a":0,"k":100,"ix":4},"w":{"a":0,"k":3,"ix":5},"lc":1,"lj":1,"ml":4,"bm":0,"nm":"Stroke 1","mn":"ADBE Vector Graphic - Stroke","hd":false},{"ty":"fl","c":{"a":0,"k":[0.992156922583,0.403921598547,0.090196078431,1],"ix":4},"o":{"a":0,"k":100,"ix":5},"r":1,"bm":0,"nm":"Fill 1","mn":"ADBE Vector Graphic - Fill","hd":false},{"ty":"tr","p":{"a":0,"k":[0,0],"ix":2},"a":{"a":0,"k":[0,0],"ix":1},"s":{"a":0,"k":[100,100],"ix":3},"r":{"a":0,"k":0,"ix":6},"o":{"a":0,"k":100,"ix":7},"sk":{"a":0,"k":0,"ix":4},"sa":{"a":0,"k":0,"ix":5},"nm":"Transform"}],"nm":"Shape 1","np":3,"cix":2,"bm":0,"ix":2,"mn":"ADBE Vector Group","hd":false}],"ip":91.000003706506,"op":428.000017432797,"st":0,"bm":0},{"ddd":0,"ind":6,"ty":4,"nm":"V 2 Outlines","parent":1,"sr":1,"ks":{"o":{"a":1,"k":[{"i":{"x":[0.833],"y":[0.833]},"o":{"x":[0.167],"y":[0.167]},"t":71,"s":[0]},{"i":{"x":[0.833],"y":[0.833]},"o":{"x":[0.167],"y":[0.167]},"t":74,"s":[100]},{"i":{"x":[0.833],"y":[0.833]},"o":{"x":[0.167],"y":[0.167]},"t":420,"s":[100]},{"t":423.000017229143,"s":[0]}],"ix":11},"r":{"a":0,"k":0,"ix":10},"p":{"a":0,"k":[-207,93,0],"ix":2},"a":{"a":0,"k":[2,-11.5,0],"ix":1},"s":{"a":0,"k":[100,100,100],"ix":6}},"ao":0,"shapes":[{"ty":"gr","it":[{"ind":0,"ty":"sh","ix":1,"ks":{"a":0,"k":{"i":[[0,0],[0,0],[0,0],[0,0],[0,0],[0,0],[0,0]],"o":[[0,0],[0,0],[0,0],[0,0],[0,0],[0,0],[0,0]],"v":[[5.59,0],[14.306,-24.338],[9.093,-24.338],[3.133,-6.325],[-3.026,-24.338],[-8.355,-24.338],[0.344,0]],"c":true},"ix":2},"nm":"V","mn":"ADBE Vector Shape - Group","hd":false},{"ty":"fl","c":{"a":0,"k":[0.129411764706,0.792156922583,0.658823529412,1],"ix":4},"o":{"a":0,"k":100,"ix":5},"r":1,"bm":0,"nm":"Fill 1","mn":"ADBE Vector Graphic - Fill","hd":false},{"ty":"tr","p":{"a":0,"k":[0,0],"ix":2},"a":{"a":0,"k":[0,0],"ix":1},"s":{"a":0,"k":[100,100],"ix":3},"r":{"a":0,"k":0,"ix":6},"o":{"a":0,"k":100,"ix":7},"sk":{"a":0,"k":0,"ix":4},"sa":{"a":0,"k":0,"ix":5},"nm":"Transform"}],"nm":"V","np":3,"cix":2,"bm":0,"ix":1,"mn":"ADBE Vector Group","hd":false}],"ip":65.0000026475043,"op":428.000017432797,"st":0,"bm":0},{"ddd":0,"ind":7,"ty":4,"nm":"V  Outlines","parent":1,"sr":1,"ks":{"o":{"a":1,"k":[{"i":{"x":[0.833],"y":[0.833]},"o":{"x":[0.167],"y":[0.167]},"t":92,"s":[0]},{"i":{"x":[0.833],"y":[0.833]},"o":{"x":[0.167],"y":[0.167]},"t":95,"s":[100]},{"i":{"x":[0.833],"y":[0.833]},"o":{"x":[0.167],"y":[0.167]},"t":420,"s":[100]},{"t":423.000017229143,"s":[0]}],"ix":11},"r":{"a":0,"k":0,"ix":10},"p":{"a":0,"k":[-146.875,-101.063,0],"ix":2},"a":{"a":0,"k":[2,-11.5,0],"ix":1},"s":{"a":0,"k":[100,100,100],"ix":6}},"ao":0,"shapes":[{"ty":"gr","it":[{"ind":0,"ty":"sh","ix":1,"ks":{"a":0,"k":{"i":[[0,0],[0,0],[0,0],[0,0],[0,0],[0,0],[0,0]],"o":[[0,0],[0,0],[0,0],[0,0],[0,0],[0,0],[0,0]],"v":[[5.59,0],[14.306,-24.338],[9.093,-24.338],[3.133,-6.325],[-3.026,-24.338],[-8.355,-24.338],[0.344,0]],"c":true},"ix":2},"nm":"V","mn":"ADBE Vector Shape - Group","hd":false},{"ty":"fl","c":{"a":0,"k":[0.129411764706,0.792156922583,0.658823529412,1],"ix":4},"o":{"a":0,"k":100,"ix":5},"r":1,"bm":0,"nm":"Fill 1","mn":"ADBE Vector Graphic - Fill","hd":false},{"ty":"tr","p":{"a":0,"k":[0,0],"ix":2},"a":{"a":0,"k":[0,0],"ix":1},"s":{"a":0,"k":[100,100],"ix":3},"r":{"a":0,"k":0,"ix":6},"o":{"a":0,"k":100,"ix":7},"sk":{"a":0,"k":0,"ix":4},"sa":{"a":0,"k":0,"ix":5},"nm":"Transform"}],"nm":"V","np":3,"cix":2,"bm":0,"ix":1,"mn":"ADBE Vector Group","hd":false}],"ip":91.000003706506,"op":428.000017432797,"st":0,"bm":0},{"ddd":0,"ind":8,"ty":4,"nm":"Vy (after collision) Outlines","parent":1,"sr":1,"ks":{"o":{"a":1,"k":[{"i":{"x":[0.833],"y":[0.833]},"o":{"x":[0.167],"y":[0.167]},"t":92,"s":[0]},{"i":{"x":[0.833],"y":[0.833]},"o":{"x":[0.167],"y":[0.167]},"t":95,"s":[100]},{"i":{"x":[0.833],"y":[0.833]},"o":{"x":[0.167],"y":[0.167]},"t":420,"s":[100]},{"t":423.000017229143,"s":[0]}],"ix":11},"r":{"a":0,"k":0,"ix":10},"p":{"a":0,"k":[-219.063,-194.812,0],"ix":2},"a":{"a":0,"k":[2,-11.5,0],"ix":1},"s":{"a":0,"k":[100,100,100],"ix":6}},"ao":0,"shapes":[{"ty":"gr","it":[{"ind":0,"ty":"sh","ix":1,"ks":{"a":0,"k":{"i":[[0,0],[0,0],[0,0],[0,0],[0,0],[0,0],[0,0]],"o":[[0,0],[0,0],[0,0],[0,0],[0,0],[0,0],[0,0]],"v":[[-3.234,0],[5.482,-24.338],[0.269,-24.338],[-5.691,-6.325],[-11.85,-24.338],[-17.179,-24.338],[-8.48,0]],"c":true},"ix":2},"nm":"V","mn":"ADBE Vector Shape - Group","hd":false},{"ty":"fl","c":{"a":0,"k":[0.992156922583,0.403921598547,0.090196078431,1],"ix":4},"o":{"a":0,"k":100,"ix":5},"r":1,"bm":0,"nm":"Fill 1","mn":"ADBE Vector Graphic - Fill","hd":false},{"ty":"tr","p":{"a":0,"k":[0,0],"ix":2},"a":{"a":0,"k":[0,0],"ix":1},"s":{"a":0,"k":[100,100],"ix":3},"r":{"a":0,"k":0,"ix":6},"o":{"a":0,"k":100,"ix":7},"sk":{"a":0,"k":0,"ix":4},"sa":{"a":0,"k":0,"ix":5},"nm":"Transform"}],"nm":"V","np":3,"cix":2,"bm":0,"ix":1,"mn":"ADBE Vector Group","hd":false},{"ty":"gr","it":[{"ind":0,"ty":"sh","ix":1,"ks":{"a":0,"k":{"i":[[0,0],[0.52,-0.637],[1.085,0],[0.73,0.144],[0,0],[-0.896,0],[-0.703,0.188],[-0.481,0.337],[-0.371,0.542],[-0.41,1.029],[0,0],[0,0],[0,0],[0,0],[0,0],[0,0]],"o":[[-0.277,0.985],[-0.52,0.636],[-0.587,0],[0,0],[0.863,0.188],[0.885,0],[0.703,-0.188],[0.481,-0.338],[0.371,-0.542],[0,0],[0,0],[0,0],[0,0],[0,0],[0,0],[0,0]],"v":[[11.193,0.05],[9.998,2.482],[7.59,3.437],[5.615,3.221],[6.03,6.873],[8.669,7.155],[11.052,6.873],[12.828,6.084],[14.106,4.765],[15.277,2.407],[16.389,-0.664],[22.615,-17.631],[17.784,-17.631],[13.667,-5.113],[9.45,-17.631],[4.486,-17.631]],"c":true},"ix":2},"nm":"y","mn":"ADBE Vector Shape - Group","hd":false},{"ty":"fl","c":{"a":0,"k":[0.992156922583,0.403921598547,0.090196078431,1],"ix":4},"o":{"a":0,"k":100,"ix":5},"r":1,"bm":0,"nm":"Fill 1","mn":"ADBE Vector Graphic - Fill","hd":false},{"ty":"tr","p":{"a":0,"k":[0,0],"ix":2},"a":{"a":0,"k":[0,0],"ix":1},"s":{"a":0,"k":[100,100],"ix":3},"r":{"a":0,"k":0,"ix":6},"o":{"a":0,"k":100,"ix":7},"sk":{"a":0,"k":0,"ix":4},"sa":{"a":0,"k":0,"ix":5},"nm":"Transform"}],"nm":"y","np":3,"cix":2,"bm":0,"ix":2,"mn":"ADBE Vector Group","hd":false},{"ty":"gr","it":[{"ind":0,"ty":"sh","ix":1,"ks":{"a":0,"k":{"i":[[0.205,0.598],[0.179,1.008],[0,0.961],[-0.302,1.245],[-0.803,1.775],[0,0],[0.504,-1.312],[0,-1.693],[-0.469,-1.459],[-0.896,-1.354],[0,0]],"o":[[-0.311,-0.908],[-0.179,-1.008],[0,-1.394],[0.302,-1.245],[0,0],[-0.773,1.107],[-0.58,1.512],[0,1.365],[0.469,1.459],[0,0],[-0.516,-1.119]],"v":[[-57.201,28.213],[-57.935,25.339],[-58.203,22.386],[-57.75,18.426],[-56.093,13.896],[-57.781,13.896],[-59.697,17.525],[-60.567,22.333],[-59.864,26.569],[-57.816,30.788],[-56.12,30.788]],"c":true},"ix":2},"nm":"(","mn":"ADBE Vector Shape - Group","hd":false},{"ty":"fl","c":{"a":0,"k":[0.992156922583,0.403921598547,0.090196078431,1],"ix":4},"o":{"a":0,"k":100,"ix":5},"r":1,"bm":0,"nm":"Fill 1","mn":"ADBE Vector Graphic - Fill","hd":false},{"ty":"tr","p":{"a":0,"k":[0,0],"ix":2},"a":{"a":0,"k":[0,0],"ix":1},"s":{"a":0,"k":[100,100],"ix":3},"r":{"a":0,"k":0,"ix":6},"o":{"a":0,"k":100,"ix":7},"sk":{"a":0,"k":0,"ix":4},"sa":{"a":0,"k":0,"ix":5},"nm":"Transform"}],"nm":"(","np":3,"cix":2,"bm":0,"ix":3,"mn":"ADBE Vector Group","hd":false},{"ty":"gr","it":[{"ind":0,"ty":"sh","ix":1,"ks":{"a":0,"k":{"i":[[-0.246,0.173],[-0.439,0],[-0.234,-0.202],[0,-0.475],[0,0],[1.154,-0.217],[0.454,-0.22],[0.252,-0.413],[0,-0.527],[-0.554,-0.521],[-0.961,0],[-0.481,0.205],[-0.422,0.41],[-0.041,-0.146],[-0.065,-0.164],[0,0],[0.079,0.39],[0,0.82],[0,0],[0.22,0.401],[0.539,0.261],[1.102,0],[0.615,-0.434],[0.252,-0.902],[0,0]],"o":[[0.246,-0.173],[0.65,0],[0.234,0.202],[0,0],[-0.445,0.188],[-0.856,0.164],[-0.454,0.22],[-0.252,0.413],[0,0.797],[0.554,0.522],[0.545,0],[0.48,-0.205],[0.018,0.047],[0.094,0.322],[0,0],[-0.217,-0.445],[-0.079,-0.39],[0,0],[0,-1.072],[-0.22,-0.401],[-0.539,-0.261],[-1.213,0],[-0.615,0.434],[0,0],[0.152,-0.434]],"v":[[-51.778,19.604],[-50.75,19.345],[-49.422,19.648],[-49.071,20.663],[-49.071,20.909],[-51.47,21.516],[-53.435,22.091],[-54.494,23.041],[-54.872,24.451],[-54.041,26.429],[-51.769,27.211],[-50.231,26.903],[-48.877,25.98],[-48.79,26.271],[-48.552,27],[-46.109,27],[-46.553,25.748],[-46.671,23.933],[-46.645,21.05],[-46.975,18.839],[-48.113,17.846],[-50.574,17.455],[-53.316,18.105],[-54.617,20.109],[-52.375,20.514]],"c":true},"ix":2},"nm":"a","mn":"ADBE Vector Shape - Group","hd":false},{"ind":1,"ty":"sh","ix":2,"ks":{"a":0,"k":{"i":[[0,0],[0.064,-0.211],[0.299,-0.223],[0.445,0],[0.258,0.252],[0,0.346],[-0.322,0.229],[-0.686,0.147],[-0.316,0.105]],"o":[[0,0.592],[-0.094,0.322],[-0.404,0.293],[-0.399,0],[-0.258,-0.252],[0,-0.352],[0.211,-0.141],[0.686,-0.146],[0,0]],"v":[[-49.071,23.01],[-49.167,24.214],[-49.756,25.031],[-51.031,25.471],[-52.015,25.093],[-52.402,24.196],[-51.918,23.326],[-50.574,22.896],[-49.071,22.518]],"c":true},"ix":2},"nm":"a","mn":"ADBE Vector Shape - Group","hd":false},{"ty":"mm","mm":1,"nm":"Merge Paths 1","mn":"ADBE Vector Filter - Merge","hd":false},{"ty":"fl","c":{"a":0,"k":[0.992156922583,0.403921598547,0.090196078431,1],"ix":4},"o":{"a":0,"k":100,"ix":5},"r":1,"bm":0,"nm":"Fill 1","mn":"ADBE Vector Graphic - Fill","hd":false},{"ty":"tr","p":{"a":0,"k":[0,0],"ix":2},"a":{"a":0,"k":[0,0],"ix":1},"s":{"a":0,"k":[100,100],"ix":3},"r":{"a":0,"k":0,"ix":6},"o":{"a":0,"k":100,"ix":7},"sk":{"a":0,"k":0,"ix":4},"sa":{"a":0,"k":0,"ix":5},"nm":"Transform"}],"nm":"a","np":5,"cix":2,"bm":0,"ix":4,"mn":"ADBE Vector Group","hd":false},{"ty":"gr","it":[{"ind":0,"ty":"sh","ix":1,"ks":{"a":0,"k":{"i":[[0,0],[0,0],[0,0],[0,0],[0,0],[0,0],[0,0],[0,0],[0,0],[-0.155,0.167],[-0.357,0],[-0.393,-0.094],[0,0],[0.703,0],[0.448,-0.243],[0.167,-0.387],[0,-0.785],[0,0],[0,0]],"o":[[0,0],[0,0],[0,0],[0,0],[0,0],[0,0],[0,0],[0,0],[0,-0.475],[0.155,-0.167],[0.363,0],[0,0],[-0.674,-0.211],[-0.686,0],[-0.448,0.243],[-0.167,0.387],[0,0],[0,0],[0,0]],"v":[[-45.292,19.608],[-43.92,19.608],[-43.92,27],[-41.451,27],[-41.451,19.608],[-39.605,19.608],[-39.605,17.666],[-41.451,17.666],[-41.451,17.007],[-41.218,16.044],[-40.449,15.794],[-39.315,15.935],[-38.981,14.212],[-41.046,13.896],[-42.747,14.26],[-43.67,15.205],[-43.92,16.963],[-43.92,17.666],[-45.292,17.666]],"c":true},"ix":2},"nm":"f","mn":"ADBE Vector Shape - Group","hd":false},{"ty":"fl","c":{"a":0,"k":[0.992156922583,0.403921598547,0.090196078431,1],"ix":4},"o":{"a":0,"k":100,"ix":5},"r":1,"bm":0,"nm":"Fill 1","mn":"ADBE Vector Graphic - Fill","hd":false},{"ty":"tr","p":{"a":0,"k":[0,0],"ix":2},"a":{"a":0,"k":[0,0],"ix":1},"s":{"a":0,"k":[100,100],"ix":3},"r":{"a":0,"k":0,"ix":6},"o":{"a":0,"k":100,"ix":7},"sk":{"a":0,"k":0,"ix":4},"sa":{"a":0,"k":0,"ix":5},"nm":"Transform"}],"nm":"f","np":3,"cix":2,"bm":0,"ix":5,"mn":"ADBE Vector Group","hd":false},{"ty":"gr","it":[{"ind":0,"ty":"sh","ix":1,"ks":{"a":0,"k":{"i":[[0,0],[0,0],[0,0],[0,0],[0,0],[0,0],[0,0],[0,0],[-0.053,-0.287],[-0.167,-0.237],[-0.357,-0.149],[-0.445,0],[-0.574,0.246],[0,0],[0.229,0],[0.114,0.082],[0.032,0.126],[0,0.762],[0,0],[0,0],[0,0]],"o":[[0,0],[0,0],[0,0],[0,0],[0,0],[0,0],[0,0],[0,0.873],[0.064,0.404],[0.167,0.237],[0.357,0.149],[0.726,0],[0,0],[-0.434,0.158],[-0.164,0],[-0.114,-0.082],[-0.032,-0.126],[0,0],[0,0],[0,0],[0,0]],"v":[[-35.624,17.666],[-35.624,14.37],[-38.102,15.812],[-38.102,17.666],[-39.236,17.666],[-39.236,19.635],[-38.102,19.635],[-38.102,23.704],[-38.023,25.444],[-37.676,26.407],[-36.889,26.987],[-35.685,27.211],[-33.734,26.842],[-33.945,24.926],[-34.938,25.163],[-35.355,25.04],[-35.575,24.728],[-35.624,23.396],[-35.624,19.635],[-33.936,19.635],[-33.936,17.666]],"c":true},"ix":2},"nm":"t","mn":"ADBE Vector Shape - Group","hd":false},{"ty":"fl","c":{"a":0,"k":[0.992156922583,0.403921598547,0.090196078431,1],"ix":4},"o":{"a":0,"k":100,"ix":5},"r":1,"bm":0,"nm":"Fill 1","mn":"ADBE Vector Graphic - Fill","hd":false},{"ty":"tr","p":{"a":0,"k":[0,0],"ix":2},"a":{"a":0,"k":[0,0],"ix":1},"s":{"a":0,"k":[100,100],"ix":3},"r":{"a":0,"k":0,"ix":6},"o":{"a":0,"k":100,"ix":7},"sk":{"a":0,"k":0,"ix":4},"sa":{"a":0,"k":0,"ix":5},"nm":"Transform"}],"nm":"t","np":3,"cix":2,"bm":0,"ix":6,"mn":"ADBE Vector Group","hd":false},{"ty":"gr","it":[{"ind":0,"ty":"sh","ix":1,"ks":{"a":0,"k":{"i":[[0.264,-0.211],[0.387,0],[0.381,0.407],[0.018,0.733],[0,0],[0.803,0.917],[1.389,0],[0.809,-0.876],[0,-1.547],[-0.615,-0.85],[-1.623,0],[-0.683,0.472],[-0.316,0.902],[0,0]],"o":[[-0.264,0.211],[-0.568,0],[-0.381,-0.407],[0,0],[0.035,-1.893],[-0.803,-0.917],[-1.236,0],[-0.809,0.876],[0,1.295],[0.779,1.061],[1.025,0],[0.683,-0.472],[0,0],[-0.135,0.469]],"v":[[-27.415,25.049],[-28.39,25.365],[-29.814,24.754],[-30.412,23.045],[-24.224,23.045],[-25.375,18.831],[-28.663,17.455],[-31.73,18.769],[-32.943,22.403],[-32.02,25.62],[-28.417,27.211],[-25.854,26.503],[-24.356,24.442],[-26.817,24.029]],"c":true},"ix":2},"nm":"e","mn":"ADBE Vector Shape - Group","hd":false},{"ind":1,"ty":"sh","ix":2,"ks":{"a":0,"k":{"i":[[0,0],[-0.352,0.393],[-0.539,0],[-0.352,-0.372],[-0.018,-0.715]],"o":[[-0.006,-0.674],[0.352,-0.392],[0.504,0],[0.352,0.372],[0,0]],"v":[[-30.368,21.533],[-29.849,19.934],[-28.513,19.345],[-27.23,19.903],[-26.676,21.533]],"c":true},"ix":2},"nm":"e","mn":"ADBE Vector Shape - Group","hd":false},{"ty":"mm","mm":1,"nm":"Merge Paths 1","mn":"ADBE Vector Filter - Merge","hd":false},{"ty":"fl","c":{"a":0,"k":[0.992156922583,0.403921598547,0.090196078431,1],"ix":4},"o":{"a":0,"k":100,"ix":5},"r":1,"bm":0,"nm":"Fill 1","mn":"ADBE Vector Graphic - Fill","hd":false},{"ty":"tr","p":{"a":0,"k":[0,0],"ix":2},"a":{"a":0,"k":[0,0],"ix":1},"s":{"a":0,"k":[100,100],"ix":3},"r":{"a":0,"k":0,"ix":6},"o":{"a":0,"k":100,"ix":7},"sk":{"a":0,"k":0,"ix":4},"sa":{"a":0,"k":0,"ix":5},"nm":"Transform"}],"nm":"e","np":5,"cix":2,"bm":0,"ix":7,"mn":"ADBE Vector Group","hd":false},{"ty":"gr","it":[{"ind":0,"ty":"sh","ix":1,"ks":{"a":0,"k":{"i":[[0,0],[-0.138,0.498],[-0.24,0.19],[-0.346,0],[-0.416,-0.269],[0,0],[0.562,0],[0.313,-0.199],[0.392,-0.627],[0,0],[0,0],[0,0],[0,0]],"o":[[0,-1.588],[0.138,-0.498],[0.24,-0.19],[0.357,0],[0,0],[-0.522,-0.311],[-0.399,0],[-0.314,0.199],[0,0],[0,0],[0,0],[0,0],[0,0]],"v":[[-19.847,24.117],[-19.641,20.988],[-19.074,19.956],[-18.195,19.67],[-17.035,20.074],[-16.27,17.921],[-17.896,17.455],[-18.964,17.754],[-20.023,18.993],[-20.023,17.666],[-22.317,17.666],[-22.317,27],[-19.847,27]],"c":true},"ix":2},"nm":"r","mn":"ADBE Vector Shape - Group","hd":false},{"ty":"fl","c":{"a":0,"k":[0.992156922583,0.403921598547,0.090196078431,1],"ix":4},"o":{"a":0,"k":100,"ix":5},"r":1,"bm":0,"nm":"Fill 1","mn":"ADBE Vector Graphic - Fill","hd":false},{"ty":"tr","p":{"a":0,"k":[0,0],"ix":2},"a":{"a":0,"k":[0,0],"ix":1},"s":{"a":0,"k":[100,100],"ix":3},"r":{"a":0,"k":0,"ix":6},"o":{"a":0,"k":100,"ix":7},"sk":{"a":0,"k":0,"ix":4},"sa":{"a":0,"k":0,"ix":5},"nm":"Transform"}],"nm":"r","np":3,"cix":2,"bm":0,"ix":8,"mn":"ADBE Vector Group","hd":false},{"ty":"gr","it":[{"ind":0,"ty":"sh","ix":1,"ks":{"a":0,"k":{"i":[[0.671,0.489],[1.137,0],[0.814,-0.858],[0,-1.541],[-0.812,-0.861],[-1.365,0],[-0.715,0.568],[-0.252,1.113],[0,0],[0.299,-0.267],[0.469,0],[0.372,0.457],[0,1.107],[-0.366,0.425],[-0.615,0],[-0.29,-0.246],[-0.082,-0.486],[0,0]],"o":[[-0.671,-0.489],[-1.389,0],[-0.814,0.858],[0,1.524],[0.811,0.861],[1.201,0],[0.715,-0.568],[0,0],[-0.123,0.65],[-0.299,0.267],[-0.627,0],[-0.372,-0.457],[0,-0.996],[0.366,-0.425],[0.463,0],[0.29,0.246],[0,0],[-0.293,-1.002]],"v":[[-3.513,18.189],[-6.224,17.455],[-9.529,18.743],[-10.75,22.342],[-9.533,25.919],[-6.268,27.211],[-3.394,26.358],[-1.944,23.836],[-4.37,23.423],[-5.002,24.798],[-6.154,25.198],[-7.652,24.513],[-8.21,22.166],[-7.661,20.035],[-6.189,19.397],[-5.06,19.767],[-4.501,20.865],[-2.067,20.426]],"c":true},"ix":2},"nm":"c","mn":"ADBE Vector Shape - Group","hd":false},{"ty":"fl","c":{"a":0,"k":[0.992156922583,0.403921598547,0.090196078431,1],"ix":4},"o":{"a":0,"k":100,"ix":5},"r":1,"bm":0,"nm":"Fill 1","mn":"ADBE Vector Graphic - Fill","hd":false},{"ty":"tr","p":{"a":0,"k":[0,0],"ix":2},"a":{"a":0,"k":[0,0],"ix":1},"s":{"a":0,"k":[100,100],"ix":3},"r":{"a":0,"k":0,"ix":6},"o":{"a":0,"k":100,"ix":7},"sk":{"a":0,"k":0,"ix":4},"sa":{"a":0,"k":0,"ix":5},"nm":"Transform"}],"nm":"c","np":3,"cix":2,"bm":0,"ix":9,"mn":"ADBE Vector Group","hd":false},{"ty":"gr","it":[{"ind":0,"ty":"sh","ix":1,"ks":{"a":0,"k":{"i":[[-0.404,-0.747],[-0.776,-0.387],[-0.856,0],[-0.911,0.929],[0,1.412],[0.902,0.917],[1.412,0],[0.741,-0.404],[0.404,-0.768],[0,-0.82]],"o":[[0.404,0.747],[0.776,0.387],[1.383,0],[0.911,-0.929],[0,-1.4],[-0.902,-0.917],[-0.914,0],[-0.741,0.404],[-0.404,0.768],[0,1.072]],"v":[[-0.16,24.93],[1.611,26.631],[4.059,27.211],[7.5,25.818],[8.867,22.307],[7.513,18.831],[4.042,17.455],[1.559,18.062],[-0.16,19.819],[-0.766,22.201]],"c":true},"ix":2},"nm":"o","mn":"ADBE Vector Shape - Group","hd":false},{"ind":1,"ty":"sh","ix":2,"ks":{"a":0,"k":{"i":[[-0.439,0.492],[-0.645,0],[-0.437,-0.492],[0,-0.914],[0.436,-0.492],[0.644,0],[0.439,0.492],[0,0.926]],"o":[[0.439,-0.492],[0.644,0],[0.436,0.492],[0,0.938],[-0.437,0.492],[-0.645,0],[-0.439,-0.492],[0,-0.926]],"v":[[2.424,20.206],[4.05,19.468],[5.672,20.206],[6.327,22.315],[5.672,24.46],[4.05,25.198],[2.424,24.46],[1.765,22.333]],"c":true},"ix":2},"nm":"o","mn":"ADBE Vector Shape - Group","hd":false},{"ty":"mm","mm":1,"nm":"Merge Paths 1","mn":"ADBE Vector Filter - Merge","hd":false},{"ty":"fl","c":{"a":0,"k":[0.992156922583,0.403921598547,0.090196078431,1],"ix":4},"o":{"a":0,"k":100,"ix":5},"r":1,"bm":0,"nm":"Fill 1","mn":"ADBE Vector Graphic - Fill","hd":false},{"ty":"tr","p":{"a":0,"k":[0,0],"ix":2},"a":{"a":0,"k":[0,0],"ix":1},"s":{"a":0,"k":[100,100],"ix":3},"r":{"a":0,"k":0,"ix":6},"o":{"a":0,"k":100,"ix":7},"sk":{"a":0,"k":0,"ix":4},"sa":{"a":0,"k":0,"ix":5},"nm":"Transform"}],"nm":"o","np":5,"cix":2,"bm":0,"ix":10,"mn":"ADBE Vector Group","hd":false},{"ty":"gr","it":[{"ind":0,"ty":"sh","ix":1,"ks":{"a":0,"k":{"i":[[0,0],[0,0],[0,0],[0,0]],"o":[[0,0],[0,0],[0,0],[0,0]],"v":[[13.27,27],[13.27,14.115],[10.8,14.115],[10.8,27]],"c":true},"ix":2},"nm":"l","mn":"ADBE Vector Shape - Group","hd":false},{"ty":"fl","c":{"a":0,"k":[0.992156922583,0.403921598547,0.090196078431,1],"ix":4},"o":{"a":0,"k":100,"ix":5},"r":1,"bm":0,"nm":"Fill 1","mn":"ADBE Vector Graphic - Fill","hd":false},{"ty":"tr","p":{"a":0,"k":[0,0],"ix":2},"a":{"a":0,"k":[0,0],"ix":1},"s":{"a":0,"k":[100,100],"ix":3},"r":{"a":0,"k":0,"ix":6},"o":{"a":0,"k":100,"ix":7},"sk":{"a":0,"k":0,"ix":4},"sa":{"a":0,"k":0,"ix":5},"nm":"Transform"}],"nm":"l","np":3,"cix":2,"bm":0,"ix":11,"mn":"ADBE Vector Group","hd":false},{"ty":"gr","it":[{"ind":0,"ty":"sh","ix":1,"ks":{"a":0,"k":{"i":[[0,0],[0,0],[0,0],[0,0]],"o":[[0,0],[0,0],[0,0],[0,0]],"v":[[18.271,27],[18.271,14.115],[15.801,14.115],[15.801,27]],"c":true},"ix":2},"nm":"l","mn":"ADBE Vector Shape - Group","hd":false},{"ty":"fl","c":{"a":0,"k":[0.992156922583,0.403921598547,0.090196078431,1],"ix":4},"o":{"a":0,"k":100,"ix":5},"r":1,"bm":0,"nm":"Fill 1","mn":"ADBE Vector Graphic - Fill","hd":false},{"ty":"tr","p":{"a":0,"k":[0,0],"ix":2},"a":{"a":0,"k":[0,0],"ix":1},"s":{"a":0,"k":[100,100],"ix":3},"r":{"a":0,"k":0,"ix":6},"o":{"a":0,"k":100,"ix":7},"sk":{"a":0,"k":0,"ix":4},"sa":{"a":0,"k":0,"ix":5},"nm":"Transform"}],"nm":"l","np":3,"cix":2,"bm":0,"ix":12,"mn":"ADBE Vector Group","hd":false},{"ty":"gr","it":[{"ind":0,"ty":"sh","ix":1,"ks":{"a":0,"k":{"i":[[0,0],[0,0],[0,0],[0,0]],"o":[[0,0],[0,0],[0,0],[0,0]],"v":[[23.272,16.4],[23.272,14.115],[20.802,14.115],[20.802,16.4]],"c":true},"ix":2},"nm":"i","mn":"ADBE Vector Shape - Group","hd":false},{"ind":1,"ty":"sh","ix":2,"ks":{"a":0,"k":{"i":[[0,0],[0,0],[0,0],[0,0]],"o":[[0,0],[0,0],[0,0],[0,0]],"v":[[23.272,27],[23.272,17.666],[20.802,17.666],[20.802,27]],"c":true},"ix":2},"nm":"i","mn":"ADBE Vector Shape - Group","hd":false},{"ty":"mm","mm":1,"nm":"Merge Paths 1","mn":"ADBE Vector Filter - Merge","hd":false},{"ty":"fl","c":{"a":0,"k":[0.992156922583,0.403921598547,0.090196078431,1],"ix":4},"o":{"a":0,"k":100,"ix":5},"r":1,"bm":0,"nm":"Fill 1","mn":"ADBE Vector Graphic - Fill","hd":false},{"ty":"tr","p":{"a":0,"k":[0,0],"ix":2},"a":{"a":0,"k":[0,0],"ix":1},"s":{"a":0,"k":[100,100],"ix":3},"r":{"a":0,"k":0,"ix":6},"o":{"a":0,"k":100,"ix":7},"sk":{"a":0,"k":0,"ix":4},"sa":{"a":0,"k":0,"ix":5},"nm":"Transform"}],"nm":"i","np":5,"cix":2,"bm":0,"ix":13,"mn":"ADBE Vector Group","hd":false},{"ty":"gr","it":[{"ind":0,"ty":"sh","ix":1,"ks":{"a":0,"k":{"i":[[-0.741,-0.516],[-1.272,0],[-0.715,0.615],[0,0.856],[0.516,0.439],[1.315,0.299],[0.223,0.164],[0,0.176],[-0.188,0.129],[-0.65,0],[-0.278,-0.193],[-0.1,-0.363],[0,0],[0.621,0.416],[1.277,0],[0.639,-0.551],[0,-0.809],[-0.738,-0.504],[-1.992,-0.439],[-0.123,-0.117],[0,-0.187],[0.217,-0.164],[0.639,0],[0.322,0.249],[0.105,0.481],[0,0]],"o":[[0.741,0.516],[1.4,0],[0.715,-0.615],[0,-0.785],[-0.522,-0.434],[-1.315,-0.299],[-0.164,-0.123],[0,-0.205],[0.281,-0.182],[0.516,0],[0.278,0.193],[0,0],[-0.234,-0.814],[-0.621,-0.416],[-1.342,0],[-0.639,0.551],[0,0.896],[0.533,0.363],[0.428,0.1],[0.117,0.123],[0,0.275],[-0.322,0.234],[-0.58,0],[-0.322,-0.249],[0,0],[0.229,0.885]],"v":[[26.388,26.438],[29.407,27.211],[32.58,26.288],[33.652,24.082],[32.878,22.245],[30.123,21.146],[27.816,20.452],[27.57,20.004],[27.851,19.503],[29.249,19.23],[30.439,19.521],[31.006,20.355],[33.335,19.925],[32.052,18.079],[29.205,17.455],[26.234,18.281],[25.276,20.32],[26.383,22.421],[30.171,23.625],[30.998,23.95],[31.173,24.416],[30.848,25.075],[29.407,25.427],[28.053,25.053],[27.412,23.959],[24.933,24.337]],"c":true},"ix":2},"nm":"s","mn":"ADBE Vector Shape - Group","hd":false},{"ty":"fl","c":{"a":0,"k":[0.992156922583,0.403921598547,0.090196078431,1],"ix":4},"o":{"a":0,"k":100,"ix":5},"r":1,"bm":0,"nm":"Fill 1","mn":"ADBE Vector Graphic - Fill","hd":false},{"ty":"tr","p":{"a":0,"k":[0,0],"ix":2},"a":{"a":0,"k":[0,0],"ix":1},"s":{"a":0,"k":[100,100],"ix":3},"r":{"a":0,"k":0,"ix":6},"o":{"a":0,"k":100,"ix":7},"sk":{"a":0,"k":0,"ix":4},"sa":{"a":0,"k":0,"ix":5},"nm":"Transform"}],"nm":"s","np":3,"cix":2,"bm":0,"ix":14,"mn":"ADBE Vector Group","hd":false},{"ty":"gr","it":[{"ind":0,"ty":"sh","ix":1,"ks":{"a":0,"k":{"i":[[0,0],[0,0],[0,0],[0,0]],"o":[[0,0],[0,0],[0,0],[0,0]],"v":[[38.284,16.4],[38.284,14.115],[35.814,14.115],[35.814,16.4]],"c":true},"ix":2},"nm":"i","mn":"ADBE Vector Shape - Group","hd":false},{"ind":1,"ty":"sh","ix":2,"ks":{"a":0,"k":{"i":[[0,0],[0,0],[0,0],[0,0]],"o":[[0,0],[0,0],[0,0],[0,0]],"v":[[38.284,27],[38.284,17.666],[35.814,17.666],[35.814,27]],"c":true},"ix":2},"nm":"i","mn":"ADBE Vector Shape - Group","hd":false},{"ty":"mm","mm":1,"nm":"Merge Paths 1","mn":"ADBE Vector Filter - Merge","hd":false},{"ty":"fl","c":{"a":0,"k":[0.992156922583,0.403921598547,0.090196078431,1],"ix":4},"o":{"a":0,"k":100,"ix":5},"r":1,"bm":0,"nm":"Fill 1","mn":"ADBE Vector Graphic - Fill","hd":false},{"ty":"tr","p":{"a":0,"k":[0,0],"ix":2},"a":{"a":0,"k":[0,0],"ix":1},"s":{"a":0,"k":[100,100],"ix":3},"r":{"a":0,"k":0,"ix":6},"o":{"a":0,"k":100,"ix":7},"sk":{"a":0,"k":0,"ix":4},"sa":{"a":0,"k":0,"ix":5},"nm":"Transform"}],"nm":"i","np":5,"cix":2,"bm":0,"ix":15,"mn":"ADBE Vector Group","hd":false},{"ty":"gr","it":[{"ind":0,"ty":"sh","ix":1,"ks":{"a":0,"k":{"i":[[-0.404,-0.747],[-0.776,-0.387],[-0.856,0],[-0.911,0.929],[0,1.412],[0.902,0.917],[1.412,0],[0.741,-0.404],[0.404,-0.768],[0,-0.82]],"o":[[0.404,0.747],[0.776,0.387],[1.383,0],[0.911,-0.929],[0,-1.4],[-0.902,-0.917],[-0.914,0],[-0.741,0.404],[-0.404,0.768],[0,1.072]],"v":[[40.85,24.93],[42.621,26.631],[45.069,27.211],[48.51,25.818],[49.876,22.307],[48.523,18.831],[45.051,17.455],[42.568,18.062],[40.85,19.819],[40.244,22.201]],"c":true},"ix":2},"nm":"o","mn":"ADBE Vector Shape - Group","hd":false},{"ind":1,"ty":"sh","ix":2,"ks":{"a":0,"k":{"i":[[-0.439,0.492],[-0.645,0],[-0.437,-0.492],[0,-0.914],[0.436,-0.492],[0.644,0],[0.439,0.492],[0,0.926]],"o":[[0.439,-0.492],[0.644,0],[0.436,0.492],[0,0.938],[-0.437,0.492],[-0.645,0],[-0.439,-0.492],[0,-0.926]],"v":[[43.434,20.206],[45.06,19.468],[46.682,20.206],[47.336,22.315],[46.682,24.46],[45.06,25.198],[43.434,24.46],[42.775,22.333]],"c":true},"ix":2},"nm":"o","mn":"ADBE Vector Shape - Group","hd":false},{"ty":"mm","mm":1,"nm":"Merge Paths 1","mn":"ADBE Vector Filter - Merge","hd":false},{"ty":"fl","c":{"a":0,"k":[0.992156922583,0.403921598547,0.090196078431,1],"ix":4},"o":{"a":0,"k":100,"ix":5},"r":1,"bm":0,"nm":"Fill 1","mn":"ADBE Vector Graphic - Fill","hd":false},{"ty":"tr","p":{"a":0,"k":[0,0],"ix":2},"a":{"a":0,"k":[0,0],"ix":1},"s":{"a":0,"k":[100,100],"ix":3},"r":{"a":0,"k":0,"ix":6},"o":{"a":0,"k":100,"ix":7},"sk":{"a":0,"k":0,"ix":4},"sa":{"a":0,"k":0,"ix":5},"nm":"Transform"}],"nm":"o","np":5,"cix":2,"bm":0,"ix":16,"mn":"ADBE Vector Group","hd":false},{"ty":"gr","it":[{"ind":0,"ty":"sh","ix":1,"ks":{"a":0,"k":{"i":[[0,0],[0.091,0.387],[0.231,0.305],[0.451,0.196],[0.545,0],[0.814,-1.055],[0,0],[0,0],[0,0],[0,0],[0,0],[-0.126,0.387],[-0.34,0.234],[-0.428,0],[-0.237,-0.164],[-0.105,-0.296],[0,-1.008],[0,0],[0,0]],"o":[[0,-0.721],[-0.091,-0.387],[-0.232,-0.305],[-0.451,-0.196],[-1.236,0],[0,0],[0,0],[0,0],[0,0],[0,0],[0,-1.043],[0.126,-0.387],[0.34,-0.234],[0.334,0],[0.237,0.164],[0.105,0.296],[0,0],[0,0],[0,0]],"v":[[60.3,21.199],[60.164,19.538],[59.681,18.501],[58.657,17.75],[57.163,17.455],[54.086,19.037],[54.086,17.666],[51.792,17.666],[51.792,27],[54.262,27],[54.262,22.772],[54.451,20.628],[55.15,19.696],[56.301,19.345],[57.158,19.591],[57.672,20.281],[57.831,22.236],[57.831,27],[60.3,27]],"c":true},"ix":2},"nm":"n","mn":"ADBE Vector Shape - Group","hd":false},{"ty":"fl","c":{"a":0,"k":[0.992156922583,0.403921598547,0.090196078431,1],"ix":4},"o":{"a":0,"k":100,"ix":5},"r":1,"bm":0,"nm":"Fill 1","mn":"ADBE Vector Graphic - Fill","hd":false},{"ty":"tr","p":{"a":0,"k":[0,0],"ix":2},"a":{"a":0,"k":[0,0],"ix":1},"s":{"a":0,"k":[100,100],"ix":3},"r":{"a":0,"k":0,"ix":6},"o":{"a":0,"k":100,"ix":7},"sk":{"a":0,"k":0,"ix":4},"sa":{"a":0,"k":0,"ix":5},"nm":"Transform"}],"nm":"n","np":3,"cix":2,"bm":0,"ix":17,"mn":"ADBE Vector Group","hd":false},{"ty":"gr","it":[{"ind":0,"ty":"sh","ix":1,"ks":{"a":0,"k":{"i":[[0,0],[-0.439,1.57],[0,1.225],[0.489,1.412],[0.885,1.26],[0,0],[-0.299,-1.245],[0,-1.394],[0.082,-0.653],[0.17,-0.726],[0.199,-0.557],[0.486,-1.043]],"o":[[1.008,-1.529],[0.387,-1.4],[0,-1.453],[-0.489,-1.412],[0,0],[0.803,1.775],[0.299,1.245],[0,0.686],[-0.082,0.653],[-0.17,0.726],[-0.199,0.557],[0,0]],"v":[[63.825,30.788],[65.996,26.139],[66.576,22.201],[65.842,17.903],[63.781,13.896],[62.102,13.896],[63.754,18.426],[64.203,22.386],[64.08,24.394],[63.702,26.464],[63.148,28.389],[62.12,30.788]],"c":true},"ix":2},"nm":")","mn":"ADBE Vector Shape - Group","hd":false},{"ty":"fl","c":{"a":0,"k":[0.992156922583,0.403921598547,0.090196078431,1],"ix":4},"o":{"a":0,"k":100,"ix":5},"r":1,"bm":0,"nm":"Fill 1","mn":"ADBE Vector Graphic - Fill","hd":false},{"ty":"tr","p":{"a":0,"k":[0,0],"ix":2},"a":{"a":0,"k":[0,0],"ix":1},"s":{"a":0,"k":[100,100],"ix":3},"r":{"a":0,"k":0,"ix":6},"o":{"a":0,"k":100,"ix":7},"sk":{"a":0,"k":0,"ix":4},"sa":{"a":0,"k":0,"ix":5},"nm":"Transform"}],"nm":")","np":3,"cix":2,"bm":0,"ix":18,"mn":"ADBE Vector Group","hd":false}],"ip":91.000003706506,"op":428.000017432797,"st":0,"bm":0},{"ddd":0,"ind":9,"ty":4,"nm":"Vy (before collision) Outlines","parent":1,"sr":1,"ks":{"o":{"a":1,"k":[{"i":{"x":[0.833],"y":[0.833]},"o":{"x":[0.167],"y":[0.167]},"t":71,"s":[0]},{"i":{"x":[0.833],"y":[0.833]},"o":{"x":[0.167],"y":[0.167]},"t":74,"s":[100]},{"i":{"x":[0.833],"y":[0.833]},"o":{"x":[0.167],"y":[0.167]},"t":420,"s":[100]},{"t":423.000017229143,"s":[0]}],"ix":11},"r":{"a":0,"k":0,"ix":10},"p":{"a":0,"k":[11.688,27.312,0],"ix":2},"a":{"a":0,"k":[2,-11.5,0],"ix":1},"s":{"a":0,"k":[100,100,100],"ix":6}},"ao":0,"shapes":[{"ty":"gr","it":[{"ind":0,"ty":"sh","ix":1,"ks":{"a":0,"k":{"i":[[0,0],[0,0],[0,0],[0,0],[0,0],[0,0],[0,0]],"o":[[0,0],[0,0],[0,0],[0,0],[0,0],[0,0],[0,0]],"v":[[-3.234,0],[5.482,-24.338],[0.269,-24.338],[-5.691,-6.325],[-11.85,-24.338],[-17.179,-24.338],[-8.48,0]],"c":true},"ix":2},"nm":"V","mn":"ADBE Vector Shape - Group","hd":false},{"ty":"fl","c":{"a":0,"k":[0.992156922583,0.403921598547,0.090196078431,1],"ix":4},"o":{"a":0,"k":100,"ix":5},"r":1,"bm":0,"nm":"Fill 1","mn":"ADBE Vector Graphic - Fill","hd":false},{"ty":"tr","p":{"a":0,"k":[0,0],"ix":2},"a":{"a":0,"k":[0,0],"ix":1},"s":{"a":0,"k":[100,100],"ix":3},"r":{"a":0,"k":0,"ix":6},"o":{"a":0,"k":100,"ix":7},"sk":{"a":0,"k":0,"ix":4},"sa":{"a":0,"k":0,"ix":5},"nm":"Transform"}],"nm":"V","np":3,"cix":2,"bm":0,"ix":1,"mn":"ADBE Vector Group","hd":false},{"ty":"gr","it":[{"ind":0,"ty":"sh","ix":1,"ks":{"a":0,"k":{"i":[[0,0],[0.52,-0.637],[1.085,0],[0.73,0.144],[0,0],[-0.896,0],[-0.703,0.188],[-0.481,0.337],[-0.371,0.542],[-0.41,1.029],[0,0],[0,0],[0,0],[0,0],[0,0],[0,0]],"o":[[-0.277,0.985],[-0.52,0.636],[-0.587,0],[0,0],[0.863,0.188],[0.885,0],[0.703,-0.188],[0.481,-0.338],[0.371,-0.542],[0,0],[0,0],[0,0],[0,0],[0,0],[0,0],[0,0]],"v":[[11.193,0.05],[9.998,2.482],[7.59,3.437],[5.615,3.221],[6.03,6.873],[8.669,7.155],[11.052,6.873],[12.828,6.084],[14.106,4.765],[15.277,2.407],[16.389,-0.664],[22.615,-17.631],[17.784,-17.631],[13.667,-5.113],[9.45,-17.631],[4.486,-17.631]],"c":true},"ix":2},"nm":"y","mn":"ADBE Vector Shape - Group","hd":false},{"ty":"fl","c":{"a":0,"k":[0.992156922583,0.403921598547,0.090196078431,1],"ix":4},"o":{"a":0,"k":100,"ix":5},"r":1,"bm":0,"nm":"Fill 1","mn":"ADBE Vector Graphic - Fill","hd":false},{"ty":"tr","p":{"a":0,"k":[0,0],"ix":2},"a":{"a":0,"k":[0,0],"ix":1},"s":{"a":0,"k":[100,100],"ix":3},"r":{"a":0,"k":0,"ix":6},"o":{"a":0,"k":100,"ix":7},"sk":{"a":0,"k":0,"ix":4},"sa":{"a":0,"k":0,"ix":5},"nm":"Transform"}],"nm":"y","np":3,"cix":2,"bm":0,"ix":2,"mn":"ADBE Vector Group","hd":false},{"ty":"gr","it":[{"ind":0,"ty":"sh","ix":1,"ks":{"a":0,"k":{"i":[[0.205,0.598],[0.179,1.008],[0,0.961],[-0.302,1.245],[-0.803,1.775],[0,0],[0.504,-1.312],[0,-1.693],[-0.469,-1.459],[-0.896,-1.354],[0,0]],"o":[[-0.311,-0.908],[-0.179,-1.008],[0,-1.394],[0.302,-1.245],[0,0],[-0.773,1.107],[-0.58,1.512],[0,1.365],[0.469,1.459],[0,0],[-0.516,-1.119]],"v":[[-65.199,26.213],[-65.933,23.339],[-66.201,20.386],[-65.748,16.426],[-64.091,11.896],[-65.779,11.896],[-67.695,15.525],[-68.565,20.333],[-67.862,24.569],[-65.814,28.788],[-64.118,28.788]],"c":true},"ix":2},"nm":"(","mn":"ADBE Vector Shape - Group","hd":false},{"ty":"fl","c":{"a":0,"k":[0.992156922583,0.403921598547,0.090196078431,1],"ix":4},"o":{"a":0,"k":100,"ix":5},"r":1,"bm":0,"nm":"Fill 1","mn":"ADBE Vector Graphic - Fill","hd":false},{"ty":"tr","p":{"a":0,"k":[0,0],"ix":2},"a":{"a":0,"k":[0,0],"ix":1},"s":{"a":0,"k":[100,100],"ix":3},"r":{"a":0,"k":0,"ix":6},"o":{"a":0,"k":100,"ix":7},"sk":{"a":0,"k":0,"ix":4},"sa":{"a":0,"k":0,"ix":5},"nm":"Transform"}],"nm":"(","np":3,"cix":2,"bm":0,"ix":3,"mn":"ADBE Vector Group","hd":false},{"ty":"gr","it":[{"ind":0,"ty":"sh","ix":1,"ks":{"a":0,"k":{"i":[[0,0],[0,0],[-0.519,-0.267],[-0.533,0],[-0.759,0.861],[0,1.594],[0.744,0.823],[1.137,0],[0.762,-0.867],[0,0],[0,0],[0,0]],"o":[[0,0],[0.375,0.522],[0.519,0.267],[1.084,0],[0.759,-0.861],[0,-1.541],[-0.744,-0.823],[-1.043,0],[0,0],[0,0],[0,0],[0,0]],"v":[[-60.031,25],[-60.031,23.629],[-58.69,24.811],[-57.113,25.211],[-54.349,23.919],[-53.21,20.236],[-54.327,16.69],[-57.148,15.455],[-59.855,16.756],[-59.855,12.115],[-62.325,12.115],[-62.325,25]],"c":true},"ix":2},"nm":"b","mn":"ADBE Vector Shape - Group","hd":false},{"ind":1,"ty":"sh","ix":2,"ks":{"a":0,"k":{"i":[[-0.393,0.46],[-0.592,0],[-0.387,-0.472],[0,-1.066],[0.384,-0.466],[0.545,0],[0.428,0.656],[0,0.967]],"o":[[0.392,-0.46],[0.603,0],[0.387,0.472],[0,1.002],[-0.384,0.466],[-0.709,0],[-0.305,-0.463],[0,-0.937]],"v":[[-59.284,18.035],[-57.807,17.345],[-56.322,18.052],[-55.742,20.359],[-56.317,22.561],[-57.71,23.26],[-59.416,22.275],[-59.873,20.131]],"c":true},"ix":2},"nm":"b","mn":"ADBE Vector Shape - Group","hd":false},{"ty":"mm","mm":1,"nm":"Merge Paths 1","mn":"ADBE Vector Filter - Merge","hd":false},{"ty":"fl","c":{"a":0,"k":[0.992156922583,0.403921598547,0.090196078431,1],"ix":4},"o":{"a":0,"k":100,"ix":5},"r":1,"bm":0,"nm":"Fill 1","mn":"ADBE Vector Graphic - Fill","hd":false},{"ty":"tr","p":{"a":0,"k":[0,0],"ix":2},"a":{"a":0,"k":[0,0],"ix":1},"s":{"a":0,"k":[100,100],"ix":3},"r":{"a":0,"k":0,"ix":6},"o":{"a":0,"k":100,"ix":7},"sk":{"a":0,"k":0,"ix":4},"sa":{"a":0,"k":0,"ix":5},"nm":"Transform"}],"nm":"b","np":5,"cix":2,"bm":0,"ix":4,"mn":"ADBE Vector Group","hd":false},{"ty":"gr","it":[{"ind":0,"ty":"sh","ix":1,"ks":{"a":0,"k":{"i":[[0.264,-0.211],[0.387,0],[0.381,0.407],[0.018,0.733],[0,0],[0.803,0.917],[1.389,0],[0.809,-0.876],[0,-1.547],[-0.615,-0.85],[-1.623,0],[-0.683,0.472],[-0.316,0.902],[0,0]],"o":[[-0.264,0.211],[-0.568,0],[-0.381,-0.407],[0,0],[0.035,-1.893],[-0.803,-0.917],[-1.236,0],[-0.809,0.876],[0,1.295],[0.779,1.061],[1.025,0],[0.683,-0.472],[0,0],[-0.135,0.469]],"v":[[-46.417,23.049],[-47.392,23.365],[-48.816,22.754],[-49.414,21.045],[-43.226,21.045],[-44.377,16.831],[-47.665,15.455],[-50.732,16.769],[-51.945,20.403],[-51.022,23.62],[-47.418,25.211],[-44.856,24.503],[-43.358,22.442],[-45.819,22.029]],"c":true},"ix":2},"nm":"e","mn":"ADBE Vector Shape - Group","hd":false},{"ind":1,"ty":"sh","ix":2,"ks":{"a":0,"k":{"i":[[0,0],[-0.352,0.393],[-0.539,0],[-0.352,-0.372],[-0.018,-0.715]],"o":[[-0.006,-0.674],[0.352,-0.392],[0.504,0],[0.352,0.372],[0,0]],"v":[[-49.37,19.533],[-48.851,17.934],[-47.515,17.345],[-46.232,17.903],[-45.678,19.533]],"c":true},"ix":2},"nm":"e","mn":"ADBE Vector Shape - Group","hd":false},{"ty":"mm","mm":1,"nm":"Merge Paths 1","mn":"ADBE Vector Filter - Merge","hd":false},{"ty":"fl","c":{"a":0,"k":[0.992156922583,0.403921598547,0.090196078431,1],"ix":4},"o":{"a":0,"k":100,"ix":5},"r":1,"bm":0,"nm":"Fill 1","mn":"ADBE Vector Graphic - Fill","hd":false},{"ty":"tr","p":{"a":0,"k":[0,0],"ix":2},"a":{"a":0,"k":[0,0],"ix":1},"s":{"a":0,"k":[100,100],"ix":3},"r":{"a":0,"k":0,"ix":6},"o":{"a":0,"k":100,"ix":7},"sk":{"a":0,"k":0,"ix":4},"sa":{"a":0,"k":0,"ix":5},"nm":"Transform"}],"nm":"e","np":5,"cix":2,"bm":0,"ix":5,"mn":"ADBE Vector Group","hd":false},{"ty":"gr","it":[{"ind":0,"ty":"sh","ix":1,"ks":{"a":0,"k":{"i":[[0,0],[0,0],[0,0],[0,0],[0,0],[0,0],[0,0],[0,0],[0,0],[-0.155,0.167],[-0.357,0],[-0.393,-0.094],[0,0],[0.703,0],[0.448,-0.243],[0.167,-0.387],[0,-0.785],[0,0],[0,0]],"o":[[0,0],[0,0],[0,0],[0,0],[0,0],[0,0],[0,0],[0,0],[0,-0.475],[0.155,-0.167],[0.363,0],[0,0],[-0.674,-0.211],[-0.686,0],[-0.448,0.243],[-0.167,0.387],[0,0],[0,0],[0,0]],"v":[[-42.294,17.608],[-40.923,17.608],[-40.923,25],[-38.454,25],[-38.454,17.608],[-36.608,17.608],[-36.608,15.666],[-38.454,15.666],[-38.454,15.007],[-38.221,14.044],[-37.452,13.794],[-36.318,13.935],[-35.984,12.212],[-38.049,11.896],[-39.75,12.26],[-40.673,13.205],[-40.923,14.963],[-40.923,15.666],[-42.294,15.666]],"c":true},"ix":2},"nm":"f","mn":"ADBE Vector Shape - Group","hd":false},{"ty":"fl","c":{"a":0,"k":[0.992156922583,0.403921598547,0.090196078431,1],"ix":4},"o":{"a":0,"k":100,"ix":5},"r":1,"bm":0,"nm":"Fill 1","mn":"ADBE Vector Graphic - Fill","hd":false},{"ty":"tr","p":{"a":0,"k":[0,0],"ix":2},"a":{"a":0,"k":[0,0],"ix":1},"s":{"a":0,"k":[100,100],"ix":3},"r":{"a":0,"k":0,"ix":6},"o":{"a":0,"k":100,"ix":7},"sk":{"a":0,"k":0,"ix":4},"sa":{"a":0,"k":0,"ix":5},"nm":"Transform"}],"nm":"f","np":3,"cix":2,"bm":0,"ix":6,"mn":"ADBE Vector Group","hd":false},{"ty":"gr","it":[{"ind":0,"ty":"sh","ix":1,"ks":{"a":0,"k":{"i":[[-0.404,-0.747],[-0.776,-0.387],[-0.856,0],[-0.911,0.929],[0,1.412],[0.902,0.917],[1.412,0],[0.741,-0.404],[0.404,-0.768],[0,-0.82]],"o":[[0.404,0.747],[0.776,0.387],[1.383,0],[0.911,-0.929],[0,-1.4],[-0.902,-0.917],[-0.914,0],[-0.741,0.404],[-0.404,0.768],[0,1.072]],"v":[[-35.184,22.93],[-33.413,24.631],[-30.965,25.211],[-27.524,23.818],[-26.158,20.307],[-27.511,16.831],[-30.983,15.455],[-33.466,16.062],[-35.184,17.819],[-35.791,20.201]],"c":true},"ix":2},"nm":"o","mn":"ADBE Vector Shape - Group","hd":false},{"ind":1,"ty":"sh","ix":2,"ks":{"a":0,"k":{"i":[[-0.439,0.492],[-0.645,0],[-0.437,-0.492],[0,-0.914],[0.436,-0.492],[0.644,0],[0.439,0.492],[0,0.926]],"o":[[0.439,-0.492],[0.644,0],[0.436,0.492],[0,0.938],[-0.437,0.492],[-0.645,0],[-0.439,-0.492],[0,-0.926]],"v":[[-32.6,18.206],[-30.974,17.468],[-29.353,18.206],[-28.698,20.315],[-29.353,22.46],[-30.974,23.198],[-32.6,22.46],[-33.259,20.333]],"c":true},"ix":2},"nm":"o","mn":"ADBE Vector Shape - Group","hd":false},{"ty":"mm","mm":1,"nm":"Merge Paths 1","mn":"ADBE Vector Filter - Merge","hd":false},{"ty":"fl","c":{"a":0,"k":[0.992156922583,0.403921598547,0.090196078431,1],"ix":4},"o":{"a":0,"k":100,"ix":5},"r":1,"bm":0,"nm":"Fill 1","mn":"ADBE Vector Graphic - Fill","hd":false},{"ty":"tr","p":{"a":0,"k":[0,0],"ix":2},"a":{"a":0,"k":[0,0],"ix":1},"s":{"a":0,"k":[100,100],"ix":3},"r":{"a":0,"k":0,"ix":6},"o":{"a":0,"k":100,"ix":7},"sk":{"a":0,"k":0,"ix":4},"sa":{"a":0,"k":0,"ix":5},"nm":"Transform"}],"nm":"o","np":5,"cix":2,"bm":0,"ix":7,"mn":"ADBE Vector Group","hd":false},{"ty":"gr","it":[{"ind":0,"ty":"sh","ix":1,"ks":{"a":0,"k":{"i":[[0,0],[-0.138,0.498],[-0.24,0.19],[-0.346,0],[-0.416,-0.269],[0,0],[0.562,0],[0.313,-0.199],[0.392,-0.627],[0,0],[0,0],[0,0],[0,0]],"o":[[0,-1.588],[0.138,-0.498],[0.24,-0.19],[0.357,0],[0,0],[-0.522,-0.311],[-0.399,0],[-0.314,0.199],[0,0],[0,0],[0,0],[0,0],[0,0]],"v":[[-21.86,22.117],[-21.653,18.988],[-21.086,17.956],[-20.208,17.67],[-19.047,18.074],[-18.283,15.921],[-19.909,15.455],[-20.977,15.754],[-22.036,16.993],[-22.036,15.666],[-24.33,15.666],[-24.33,25],[-21.86,25]],"c":true},"ix":2},"nm":"r","mn":"ADBE Vector Shape - Group","hd":false},{"ty":"fl","c":{"a":0,"k":[0.992156922583,0.403921598547,0.090196078431,1],"ix":4},"o":{"a":0,"k":100,"ix":5},"r":1,"bm":0,"nm":"Fill 1","mn":"ADBE Vector Graphic - Fill","hd":false},{"ty":"tr","p":{"a":0,"k":[0,0],"ix":2},"a":{"a":0,"k":[0,0],"ix":1},"s":{"a":0,"k":[100,100],"ix":3},"r":{"a":0,"k":0,"ix":6},"o":{"a":0,"k":100,"ix":7},"sk":{"a":0,"k":0,"ix":4},"sa":{"a":0,"k":0,"ix":5},"nm":"Transform"}],"nm":"r","np":3,"cix":2,"bm":0,"ix":8,"mn":"ADBE Vector Group","hd":false},{"ty":"gr","it":[{"ind":0,"ty":"sh","ix":1,"ks":{"a":0,"k":{"i":[[0.264,-0.211],[0.387,0],[0.381,0.407],[0.018,0.733],[0,0],[0.803,0.917],[1.389,0],[0.809,-0.876],[0,-1.547],[-0.615,-0.85],[-1.623,0],[-0.683,0.472],[-0.316,0.902],[0,0]],"o":[[-0.264,0.211],[-0.568,0],[-0.381,-0.407],[0,0],[0.035,-1.893],[-0.803,-0.917],[-1.236,0],[-0.809,0.876],[0,1.295],[0.779,1.061],[1.025,0],[0.683,-0.472],[0,0],[-0.135,0.469]],"v":[[-12.412,23.049],[-13.387,23.365],[-14.811,22.754],[-15.409,21.045],[-9.221,21.045],[-10.373,16.831],[-13.66,15.455],[-16.727,16.769],[-17.94,20.403],[-17.017,23.62],[-13.414,25.211],[-10.852,24.503],[-9.353,22.442],[-11.814,22.029]],"c":true},"ix":2},"nm":"e","mn":"ADBE Vector Shape - Group","hd":false},{"ind":1,"ty":"sh","ix":2,"ks":{"a":0,"k":{"i":[[0,0],[-0.352,0.393],[-0.539,0],[-0.352,-0.372],[-0.018,-0.715]],"o":[[-0.006,-0.674],[0.352,-0.392],[0.504,0],[0.352,0.372],[0,0]],"v":[[-15.365,19.533],[-14.846,17.934],[-13.51,17.345],[-12.227,17.903],[-11.673,19.533]],"c":true},"ix":2},"nm":"e","mn":"ADBE Vector Shape - Group","hd":false},{"ty":"mm","mm":1,"nm":"Merge Paths 1","mn":"ADBE Vector Filter - Merge","hd":false},{"ty":"fl","c":{"a":0,"k":[0.992156922583,0.403921598547,0.090196078431,1],"ix":4},"o":{"a":0,"k":100,"ix":5},"r":1,"bm":0,"nm":"Fill 1","mn":"ADBE Vector Graphic - Fill","hd":false},{"ty":"tr","p":{"a":0,"k":[0,0],"ix":2},"a":{"a":0,"k":[0,0],"ix":1},"s":{"a":0,"k":[100,100],"ix":3},"r":{"a":0,"k":0,"ix":6},"o":{"a":0,"k":100,"ix":7},"sk":{"a":0,"k":0,"ix":4},"sa":{"a":0,"k":0,"ix":5},"nm":"Transform"}],"nm":"e","np":5,"cix":2,"bm":0,"ix":9,"mn":"ADBE Vector Group","hd":false},{"ty":"gr","it":[{"ind":0,"ty":"sh","ix":1,"ks":{"a":0,"k":{"i":[[0.671,0.489],[1.137,0],[0.814,-0.858],[0,-1.541],[-0.812,-0.861],[-1.365,0],[-0.715,0.568],[-0.252,1.113],[0,0],[0.299,-0.267],[0.469,0],[0.372,0.457],[0,1.107],[-0.366,0.425],[-0.615,0],[-0.29,-0.246],[-0.082,-0.486],[0,0]],"o":[[-0.671,-0.489],[-1.389,0],[-0.814,0.858],[0,1.524],[0.811,0.861],[1.201,0],[0.715,-0.568],[0,0],[-0.123,0.65],[-0.299,0.267],[-0.627,0],[-0.372,-0.457],[0,-0.996],[0.366,-0.425],[0.463,0],[0.29,0.246],[0,0],[-0.293,-1.002]],"v":[[4.485,16.189],[1.774,15.455],[-1.531,16.743],[-2.752,20.342],[-1.535,23.919],[1.73,25.211],[4.604,24.358],[6.054,21.836],[3.628,21.423],[2.996,22.798],[1.844,23.198],[0.346,22.513],[-0.212,20.166],[0.337,18.035],[1.809,17.397],[2.938,17.767],[3.497,18.865],[5.931,18.426]],"c":true},"ix":2},"nm":"c","mn":"ADBE Vector Shape - Group","hd":false},{"ty":"fl","c":{"a":0,"k":[0.992156922583,0.403921598547,0.090196078431,1],"ix":4},"o":{"a":0,"k":100,"ix":5},"r":1,"bm":0,"nm":"Fill 1","mn":"ADBE Vector Graphic - Fill","hd":false},{"ty":"tr","p":{"a":0,"k":[0,0],"ix":2},"a":{"a":0,"k":[0,0],"ix":1},"s":{"a":0,"k":[100,100],"ix":3},"r":{"a":0,"k":0,"ix":6},"o":{"a":0,"k":100,"ix":7},"sk":{"a":0,"k":0,"ix":4},"sa":{"a":0,"k":0,"ix":5},"nm":"Transform"}],"nm":"c","np":3,"cix":2,"bm":0,"ix":10,"mn":"ADBE Vector Group","hd":false},{"ty":"gr","it":[{"ind":0,"ty":"sh","ix":1,"ks":{"a":0,"k":{"i":[[-0.404,-0.747],[-0.776,-0.387],[-0.856,0],[-0.911,0.929],[0,1.412],[0.902,0.917],[1.412,0],[0.741,-0.404],[0.404,-0.768],[0,-0.82]],"o":[[0.404,0.747],[0.776,0.387],[1.383,0],[0.911,-0.929],[0,-1.4],[-0.902,-0.917],[-0.914,0],[-0.741,0.404],[-0.404,0.768],[0,1.072]],"v":[[7.838,22.93],[9.609,24.631],[12.057,25.211],[15.498,23.818],[16.865,20.307],[15.511,16.831],[12.04,15.455],[9.557,16.062],[7.838,17.819],[7.232,20.201]],"c":true},"ix":2},"nm":"o","mn":"ADBE Vector Shape - Group","hd":false},{"ind":1,"ty":"sh","ix":2,"ks":{"a":0,"k":{"i":[[-0.439,0.492],[-0.645,0],[-0.437,-0.492],[0,-0.914],[0.436,-0.492],[0.644,0],[0.439,0.492],[0,0.926]],"o":[[0.439,-0.492],[0.644,0],[0.436,0.492],[0,0.938],[-0.437,0.492],[-0.645,0],[-0.439,-0.492],[0,-0.926]],"v":[[10.422,18.206],[12.048,17.468],[13.67,18.206],[14.325,20.315],[13.67,22.46],[12.048,23.198],[10.422,22.46],[9.763,20.333]],"c":true},"ix":2},"nm":"o","mn":"ADBE Vector Shape - Group","hd":false},{"ty":"mm","mm":1,"nm":"Merge Paths 1","mn":"ADBE Vector Filter - Merge","hd":false},{"ty":"fl","c":{"a":0,"k":[0.992156922583,0.403921598547,0.090196078431,1],"ix":4},"o":{"a":0,"k":100,"ix":5},"r":1,"bm":0,"nm":"Fill 1","mn":"ADBE Vector Graphic - Fill","hd":false},{"ty":"tr","p":{"a":0,"k":[0,0],"ix":2},"a":{"a":0,"k":[0,0],"ix":1},"s":{"a":0,"k":[100,100],"ix":3},"r":{"a":0,"k":0,"ix":6},"o":{"a":0,"k":100,"ix":7},"sk":{"a":0,"k":0,"ix":4},"sa":{"a":0,"k":0,"ix":5},"nm":"Transform"}],"nm":"o","np":5,"cix":2,"bm":0,"ix":11,"mn":"ADBE Vector Group","hd":false},{"ty":"gr","it":[{"ind":0,"ty":"sh","ix":1,"ks":{"a":0,"k":{"i":[[0,0],[0,0],[0,0],[0,0]],"o":[[0,0],[0,0],[0,0],[0,0]],"v":[[21.268,25],[21.268,12.115],[18.798,12.115],[18.798,25]],"c":true},"ix":2},"nm":"l","mn":"ADBE Vector Shape - Group","hd":false},{"ty":"fl","c":{"a":0,"k":[0.992156922583,0.403921598547,0.090196078431,1],"ix":4},"o":{"a":0,"k":100,"ix":5},"r":1,"bm":0,"nm":"Fill 1","mn":"ADBE Vector Graphic - Fill","hd":false},{"ty":"tr","p":{"a":0,"k":[0,0],"ix":2},"a":{"a":0,"k":[0,0],"ix":1},"s":{"a":0,"k":[100,100],"ix":3},"r":{"a":0,"k":0,"ix":6},"o":{"a":0,"k":100,"ix":7},"sk":{"a":0,"k":0,"ix":4},"sa":{"a":0,"k":0,"ix":5},"nm":"Transform"}],"nm":"l","np":3,"cix":2,"bm":0,"ix":12,"mn":"ADBE Vector Group","hd":false},{"ty":"gr","it":[{"ind":0,"ty":"sh","ix":1,"ks":{"a":0,"k":{"i":[[0,0],[0,0],[0,0],[0,0]],"o":[[0,0],[0,0],[0,0],[0,0]],"v":[[26.269,25],[26.269,12.115],[23.799,12.115],[23.799,25]],"c":true},"ix":2},"nm":"l","mn":"ADBE Vector Shape - Group","hd":false},{"ty":"fl","c":{"a":0,"k":[0.992156922583,0.403921598547,0.090196078431,1],"ix":4},"o":{"a":0,"k":100,"ix":5},"r":1,"bm":0,"nm":"Fill 1","mn":"ADBE Vector Graphic - Fill","hd":false},{"ty":"tr","p":{"a":0,"k":[0,0],"ix":2},"a":{"a":0,"k":[0,0],"ix":1},"s":{"a":0,"k":[100,100],"ix":3},"r":{"a":0,"k":0,"ix":6},"o":{"a":0,"k":100,"ix":7},"sk":{"a":0,"k":0,"ix":4},"sa":{"a":0,"k":0,"ix":5},"nm":"Transform"}],"nm":"l","np":3,"cix":2,"bm":0,"ix":13,"mn":"ADBE Vector Group","hd":false},{"ty":"gr","it":[{"ind":0,"ty":"sh","ix":1,"ks":{"a":0,"k":{"i":[[0,0],[0,0],[0,0],[0,0]],"o":[[0,0],[0,0],[0,0],[0,0]],"v":[[31.27,14.4],[31.27,12.115],[28.8,12.115],[28.8,14.4]],"c":true},"ix":2},"nm":"i","mn":"ADBE Vector Shape - Group","hd":false},{"ind":1,"ty":"sh","ix":2,"ks":{"a":0,"k":{"i":[[0,0],[0,0],[0,0],[0,0]],"o":[[0,0],[0,0],[0,0],[0,0]],"v":[[31.27,25],[31.27,15.666],[28.8,15.666],[28.8,25]],"c":true},"ix":2},"nm":"i","mn":"ADBE Vector Shape - Group","hd":false},{"ty":"mm","mm":1,"nm":"Merge Paths 1","mn":"ADBE Vector Filter - Merge","hd":false},{"ty":"fl","c":{"a":0,"k":[0.992156922583,0.403921598547,0.090196078431,1],"ix":4},"o":{"a":0,"k":100,"ix":5},"r":1,"bm":0,"nm":"Fill 1","mn":"ADBE Vector Graphic - Fill","hd":false},{"ty":"tr","p":{"a":0,"k":[0,0],"ix":2},"a":{"a":0,"k":[0,0],"ix":1},"s":{"a":0,"k":[100,100],"ix":3},"r":{"a":0,"k":0,"ix":6},"o":{"a":0,"k":100,"ix":7},"sk":{"a":0,"k":0,"ix":4},"sa":{"a":0,"k":0,"ix":5},"nm":"Transform"}],"nm":"i","np":5,"cix":2,"bm":0,"ix":14,"mn":"ADBE Vector Group","hd":false},{"ty":"gr","it":[{"ind":0,"ty":"sh","ix":1,"ks":{"a":0,"k":{"i":[[-0.741,-0.516],[-1.272,0],[-0.715,0.615],[0,0.856],[0.516,0.439],[1.315,0.299],[0.223,0.164],[0,0.176],[-0.188,0.129],[-0.65,0],[-0.278,-0.193],[-0.1,-0.363],[0,0],[0.621,0.416],[1.277,0],[0.639,-0.551],[0,-0.809],[-0.738,-0.504],[-1.992,-0.439],[-0.123,-0.117],[0,-0.187],[0.217,-0.164],[0.639,0],[0.322,0.249],[0.105,0.481],[0,0]],"o":[[0.741,0.516],[1.4,0],[0.715,-0.615],[0,-0.785],[-0.522,-0.434],[-1.315,-0.299],[-0.164,-0.123],[0,-0.205],[0.281,-0.182],[0.516,0],[0.278,0.193],[0,0],[-0.234,-0.814],[-0.621,-0.416],[-1.342,0],[-0.639,0.551],[0,0.896],[0.533,0.363],[0.428,0.1],[0.117,0.123],[0,0.275],[-0.322,0.234],[-0.58,0],[-0.322,-0.249],[0,0],[0.229,0.885]],"v":[[34.386,24.438],[37.405,25.211],[40.578,24.288],[41.65,22.082],[40.876,20.245],[38.121,19.146],[35.814,18.452],[35.568,18.004],[35.849,17.503],[37.247,17.23],[38.438,17.521],[39.004,18.355],[41.333,17.925],[40.05,16.079],[37.203,15.455],[34.232,16.281],[33.274,18.32],[34.381,20.421],[38.169,21.625],[38.996,21.95],[39.171,22.416],[38.846,23.075],[37.405,23.427],[36.051,23.053],[35.41,21.959],[32.931,22.337]],"c":true},"ix":2},"nm":"s","mn":"ADBE Vector Shape - Group","hd":false},{"ty":"fl","c":{"a":0,"k":[0.992156922583,0.403921598547,0.090196078431,1],"ix":4},"o":{"a":0,"k":100,"ix":5},"r":1,"bm":0,"nm":"Fill 1","mn":"ADBE Vector Graphic - Fill","hd":false},{"ty":"tr","p":{"a":0,"k":[0,0],"ix":2},"a":{"a":0,"k":[0,0],"ix":1},"s":{"a":0,"k":[100,100],"ix":3},"r":{"a":0,"k":0,"ix":6},"o":{"a":0,"k":100,"ix":7},"sk":{"a":0,"k":0,"ix":4},"sa":{"a":0,"k":0,"ix":5},"nm":"Transform"}],"nm":"s","np":3,"cix":2,"bm":0,"ix":15,"mn":"ADBE Vector Group","hd":false},{"ty":"gr","it":[{"ind":0,"ty":"sh","ix":1,"ks":{"a":0,"k":{"i":[[0,0],[0,0],[0,0],[0,0]],"o":[[0,0],[0,0],[0,0],[0,0]],"v":[[46.282,14.4],[46.282,12.115],[43.812,12.115],[43.812,14.4]],"c":true},"ix":2},"nm":"i","mn":"ADBE Vector Shape - Group","hd":false},{"ind":1,"ty":"sh","ix":2,"ks":{"a":0,"k":{"i":[[0,0],[0,0],[0,0],[0,0]],"o":[[0,0],[0,0],[0,0],[0,0]],"v":[[46.282,25],[46.282,15.666],[43.812,15.666],[43.812,25]],"c":true},"ix":2},"nm":"i","mn":"ADBE Vector Shape - Group","hd":false},{"ty":"mm","mm":1,"nm":"Merge Paths 1","mn":"ADBE Vector Filter - Merge","hd":false},{"ty":"fl","c":{"a":0,"k":[0.992156922583,0.403921598547,0.090196078431,1],"ix":4},"o":{"a":0,"k":100,"ix":5},"r":1,"bm":0,"nm":"Fill 1","mn":"ADBE Vector Graphic - Fill","hd":false},{"ty":"tr","p":{"a":0,"k":[0,0],"ix":2},"a":{"a":0,"k":[0,0],"ix":1},"s":{"a":0,"k":[100,100],"ix":3},"r":{"a":0,"k":0,"ix":6},"o":{"a":0,"k":100,"ix":7},"sk":{"a":0,"k":0,"ix":4},"sa":{"a":0,"k":0,"ix":5},"nm":"Transform"}],"nm":"i","np":5,"cix":2,"bm":0,"ix":16,"mn":"ADBE Vector Group","hd":false},{"ty":"gr","it":[{"ind":0,"ty":"sh","ix":1,"ks":{"a":0,"k":{"i":[[-0.404,-0.747],[-0.776,-0.387],[-0.856,0],[-0.911,0.929],[0,1.412],[0.902,0.917],[1.412,0],[0.741,-0.404],[0.404,-0.768],[0,-0.82]],"o":[[0.404,0.747],[0.776,0.387],[1.383,0],[0.911,-0.929],[0,-1.4],[-0.902,-0.917],[-0.914,0],[-0.741,0.404],[-0.404,0.768],[0,1.072]],"v":[[48.848,22.93],[50.619,24.631],[53.067,25.211],[56.508,23.818],[57.875,20.307],[56.521,16.831],[53.049,15.455],[50.566,16.062],[48.848,17.819],[48.242,20.201]],"c":true},"ix":2},"nm":"o","mn":"ADBE Vector Shape - Group","hd":false},{"ind":1,"ty":"sh","ix":2,"ks":{"a":0,"k":{"i":[[-0.439,0.492],[-0.645,0],[-0.437,-0.492],[0,-0.914],[0.436,-0.492],[0.644,0],[0.439,0.492],[0,0.926]],"o":[[0.439,-0.492],[0.644,0],[0.436,0.492],[0,0.938],[-0.437,0.492],[-0.645,0],[-0.439,-0.492],[0,-0.926]],"v":[[51.432,18.206],[53.058,17.468],[54.68,18.206],[55.334,20.315],[54.68,22.46],[53.058,23.198],[51.432,22.46],[50.773,20.333]],"c":true},"ix":2},"nm":"o","mn":"ADBE Vector Shape - Group","hd":false},{"ty":"mm","mm":1,"nm":"Merge Paths 1","mn":"ADBE Vector Filter - Merge","hd":false},{"ty":"fl","c":{"a":0,"k":[0.992156922583,0.403921598547,0.090196078431,1],"ix":4},"o":{"a":0,"k":100,"ix":5},"r":1,"bm":0,"nm":"Fill 1","mn":"ADBE Vector Graphic - Fill","hd":false},{"ty":"tr","p":{"a":0,"k":[0,0],"ix":2},"a":{"a":0,"k":[0,0],"ix":1},"s":{"a":0,"k":[100,100],"ix":3},"r":{"a":0,"k":0,"ix":6},"o":{"a":0,"k":100,"ix":7},"sk":{"a":0,"k":0,"ix":4},"sa":{"a":0,"k":0,"ix":5},"nm":"Transform"}],"nm":"o","np":5,"cix":2,"bm":0,"ix":17,"mn":"ADBE Vector Group","hd":false},{"ty":"gr","it":[{"ind":0,"ty":"sh","ix":1,"ks":{"a":0,"k":{"i":[[0,0],[0.091,0.387],[0.231,0.305],[0.451,0.196],[0.545,0],[0.814,-1.055],[0,0],[0,0],[0,0],[0,0],[0,0],[-0.126,0.387],[-0.34,0.234],[-0.428,0],[-0.237,-0.164],[-0.105,-0.296],[0,-1.008],[0,0],[0,0]],"o":[[0,-0.721],[-0.091,-0.387],[-0.232,-0.305],[-0.451,-0.196],[-1.236,0],[0,0],[0,0],[0,0],[0,0],[0,0],[0,-1.043],[0.126,-0.387],[0.34,-0.234],[0.334,0],[0.237,0.164],[0.105,0.296],[0,0],[0,0],[0,0]],"v":[[68.298,19.199],[68.162,17.538],[67.679,16.501],[66.655,15.75],[65.161,15.455],[62.084,17.037],[62.084,15.666],[59.791,15.666],[59.791,25],[62.26,25],[62.26,20.772],[62.449,18.628],[63.148,17.696],[64.299,17.345],[65.156,17.591],[65.67,18.281],[65.829,20.236],[65.829,25],[68.298,25]],"c":true},"ix":2},"nm":"n","mn":"ADBE Vector Shape - Group","hd":false},{"ty":"fl","c":{"a":0,"k":[0.992156922583,0.403921598547,0.090196078431,1],"ix":4},"o":{"a":0,"k":100,"ix":5},"r":1,"bm":0,"nm":"Fill 1","mn":"ADBE Vector Graphic - Fill","hd":false},{"ty":"tr","p":{"a":0,"k":[0,0],"ix":2},"a":{"a":0,"k":[0,0],"ix":1},"s":{"a":0,"k":[100,100],"ix":3},"r":{"a":0,"k":0,"ix":6},"o":{"a":0,"k":100,"ix":7},"sk":{"a":0,"k":0,"ix":4},"sa":{"a":0,"k":0,"ix":5},"nm":"Transform"}],"nm":"n","np":3,"cix":2,"bm":0,"ix":18,"mn":"ADBE Vector Group","hd":false},{"ty":"gr","it":[{"ind":0,"ty":"sh","ix":1,"ks":{"a":0,"k":{"i":[[0,0],[-0.439,1.57],[0,1.225],[0.489,1.412],[0.885,1.26],[0,0],[-0.299,-1.245],[0,-1.394],[0.082,-0.653],[0.17,-0.726],[0.199,-0.557],[0.486,-1.043]],"o":[[1.008,-1.529],[0.387,-1.4],[0,-1.453],[-0.489,-1.412],[0,0],[0.803,1.775],[0.299,1.245],[0,0.686],[-0.082,0.653],[-0.17,0.726],[-0.199,0.557],[0,0]],"v":[[71.823,28.788],[73.994,24.139],[74.574,20.201],[73.84,15.903],[71.779,11.896],[70.1,11.896],[71.752,16.426],[72.201,20.386],[72.078,22.394],[71.7,24.464],[71.146,26.389],[70.118,28.788]],"c":true},"ix":2},"nm":")","mn":"ADBE Vector Shape - Group","hd":false},{"ty":"fl","c":{"a":0,"k":[0.992156922583,0.403921598547,0.090196078431,1],"ix":4},"o":{"a":0,"k":100,"ix":5},"r":1,"bm":0,"nm":"Fill 1","mn":"ADBE Vector Graphic - Fill","hd":false},{"ty":"tr","p":{"a":0,"k":[0,0],"ix":2},"a":{"a":0,"k":[0,0],"ix":1},"s":{"a":0,"k":[100,100],"ix":3},"r":{"a":0,"k":0,"ix":6},"o":{"a":0,"k":100,"ix":7},"sk":{"a":0,"k":0,"ix":4},"sa":{"a":0,"k":0,"ix":5},"nm":"Transform"}],"nm":")","np":3,"cix":2,"bm":0,"ix":19,"mn":"ADBE Vector Group","hd":false}],"ip":70.0000028511585,"op":428.000017432797,"st":0,"bm":0},{"ddd":0,"ind":10,"ty":4,"nm":"tip 6","parent":1,"sr":1,"ks":{"o":{"a":1,"k":[{"i":{"x":[0.833],"y":[0.833]},"o":{"x":[0.167],"y":[0.167]},"t":420,"s":[100]},{"t":423.000017229143,"s":[0]}],"ix":11},"r":{"a":0,"k":49.544,"ix":10},"p":{"a":1,"k":[{"i":{"x":0.833,"y":0.833},"o":{"x":0.167,"y":0.167},"t":50,"s":[-66,169.25,0],"to":[0,0,0],"ti":[0,0,0]},{"t":72.0000029326201,"s":[-66,-9,0]}],"ix":2},"a":{"a":0,"k":[-280.5,-20,0],"ix":1},"s":{"a":0,"k":[100,100,100],"ix":6}},"ao":0,"shapes":[{"ty":"gr","it":[{"ind":0,"ty":"sh","ix":1,"ks":{"a":0,"k":{"i":[[0,0],[0,0],[0,0]],"o":[[0,0],[0,0],[0,0]],"v":[[-295,-33],[-289.5,-8.5],[-271,-30]],"c":true},"ix":2},"nm":"Path 1","mn":"ADBE Vector Shape - Group","hd":false},{"ty":"fl","c":{"a":0,"k":[0.992156922583,0.403921598547,0.090196078431,1],"ix":4},"o":{"a":0,"k":100,"ix":5},"r":1,"bm":0,"nm":"Fill 1","mn":"ADBE Vector Graphic - Fill","hd":false},{"ty":"tr","p":{"a":0,"k":[0,0],"ix":2},"a":{"a":0,"k":[0,0],"ix":1},"s":{"a":0,"k":[100,100],"ix":3},"r":{"a":0,"k":0,"ix":6},"o":{"a":0,"k":100,"ix":7},"sk":{"a":0,"k":0,"ix":4},"sa":{"a":0,"k":0,"ix":5},"nm":"Transform"}],"nm":"Shape 1","np":3,"cix":2,"bm":0,"ix":1,"mn":"ADBE Vector Group","hd":false}],"ip":50.0000020365418,"op":428.000017432797,"st":0,"bm":0},{"ddd":0,"ind":11,"ty":4,"nm":"arrow","parent":1,"sr":1,"ks":{"o":{"a":1,"k":[{"i":{"x":[0.833],"y":[0.833]},"o":{"x":[0.167],"y":[0.167]},"t":420,"s":[100]},{"t":423.000017229143,"s":[0]}],"ix":11},"r":{"a":0,"k":0,"ix":10},"p":{"a":0,"k":[-66,170.25,0],"ix":2},"a":{"a":0,"k":[-66,165.25,0],"ix":1},"s":{"a":0,"k":[100,100,100],"ix":6}},"ao":0,"shapes":[{"ty":"gr","it":[{"ind":0,"ty":"sh","ix":1,"ks":{"a":0,"k":{"i":[[0,0],[0,0]],"o":[[0,0],[0,0]],"v":[[-66,165],[-66,-16]],"c":false},"ix":2},"nm":"Path 1","mn":"ADBE Vector Shape - Group","hd":false},{"ty":"st","c":{"a":0,"k":[0.990716911765,0.402096677294,0.089480186911,1],"ix":3},"o":{"a":0,"k":100,"ix":4},"w":{"a":0,"k":6,"ix":5},"lc":1,"lj":1,"ml":4,"bm":0,"nm":"Stroke 1","mn":"ADBE Vector Graphic - Stroke","hd":false},{"ty":"fl","c":{"a":0,"k":[0.678431372549,0.129411764706,0.792156922583,1],"ix":4},"o":{"a":0,"k":100,"ix":5},"r":1,"bm":0,"nm":"Fill 1","mn":"ADBE Vector Graphic - Fill","hd":false},{"ty":"tr","p":{"a":0,"k":[0,0],"ix":2},"a":{"a":0,"k":[0,0],"ix":1},"s":{"a":0,"k":[100,100],"ix":3},"r":{"a":0,"k":0,"ix":6},"o":{"a":0,"k":100,"ix":7},"sk":{"a":0,"k":0,"ix":4},"sa":{"a":0,"k":0,"ix":5},"nm":"Transform"}],"nm":"Shape 1","np":3,"cix":2,"bm":0,"ix":1,"mn":"ADBE Vector Group","hd":false},{"ty":"tm","s":{"a":1,"k":[{"i":{"x":[0.833],"y":[0.833]},"o":{"x":[0.167],"y":[0.167]},"t":50,"s":[0]},{"t":72.0000029326201,"s":[0]}],"ix":1},"e":{"a":1,"k":[{"i":{"x":[0.833],"y":[0.833]},"o":{"x":[0.167],"y":[0.167]},"t":50,"s":[0]},{"t":72.0000029326201,"s":[100]}],"ix":2},"o":{"a":0,"k":0,"ix":3},"m":1,"ix":2,"nm":"Trim Paths 1","mn":"ADBE Vector Filter - Trim","hd":false}],"ip":47.0000019143492,"op":428.000017432797,"st":0,"bm":0},{"ddd":0,"ind":12,"ty":4,"nm":"-Vx Outlines","parent":1,"sr":1,"ks":{"o":{"a":1,"k":[{"i":{"x":[0.833],"y":[0.833]},"o":{"x":[0.167],"y":[0.167]},"t":92,"s":[0]},{"i":{"x":[0.833],"y":[0.833]},"o":{"x":[0.167],"y":[0.167]},"t":95,"s":[100]},{"i":{"x":[0.833],"y":[0.833]},"o":{"x":[0.167],"y":[0.167]},"t":420,"s":[100]},{"t":423.000017229143,"s":[0]}],"ix":11},"r":{"a":0,"k":0,"ix":10},"p":{"a":0,"k":[-174.938,-6.562,0],"ix":2},"a":{"a":0,"k":[2,-11.5,0],"ix":1},"s":{"a":0,"k":[100,100,100],"ix":6}},"ao":0,"shapes":[{"ty":"gr","it":[{"ind":0,"ty":"sh","ix":1,"ks":{"a":0,"k":{"i":[[0,0],[0,0],[0,0],[0,0]],"o":[[0,0],[0,0],[0,0],[0,0]],"v":[[-12.381,-6.491],[-12.381,-11.156],[-21.545,-11.156],[-21.545,-6.491]],"c":true},"ix":2},"nm":"-","mn":"ADBE Vector Shape - Group","hd":false},{"ty":"fl","c":{"a":0,"k":[0.678431372549,0.129411764706,0.792156922583,1],"ix":4},"o":{"a":0,"k":100,"ix":5},"r":1,"bm":0,"nm":"Fill 1","mn":"ADBE Vector Graphic - Fill","hd":false},{"ty":"tr","p":{"a":0,"k":[0,0],"ix":2},"a":{"a":0,"k":[0,0],"ix":1},"s":{"a":0,"k":[100,100],"ix":3},"r":{"a":0,"k":0,"ix":6},"o":{"a":0,"k":100,"ix":7},"sk":{"a":0,"k":0,"ix":4},"sa":{"a":0,"k":0,"ix":5},"nm":"Transform"}],"nm":"-","np":3,"cix":2,"bm":0,"ix":1,"mn":"ADBE Vector Group","hd":false},{"ty":"gr","it":[{"ind":0,"ty":"sh","ix":1,"ks":{"a":0,"k":{"i":[[0,0],[0,0],[0,0],[0,0],[0,0],[0,0],[0,0]],"o":[[0,0],[0,0],[0,0],[0,0],[0,0],[0,0],[0,0]],"v":[[1.796,0],[10.512,-24.338],[5.299,-24.338],[-0.661,-6.325],[-6.82,-24.338],[-12.149,-24.338],[-3.45,0]],"c":true},"ix":2},"nm":"V","mn":"ADBE Vector Shape - Group","hd":false},{"ty":"fl","c":{"a":0,"k":[0.678431372549,0.129411764706,0.792156922583,1],"ix":4},"o":{"a":0,"k":100,"ix":5},"r":1,"bm":0,"nm":"Fill 1","mn":"ADBE Vector Graphic - Fill","hd":false},{"ty":"tr","p":{"a":0,"k":[0,0],"ix":2},"a":{"a":0,"k":[0,0],"ix":1},"s":{"a":0,"k":[100,100],"ix":3},"r":{"a":0,"k":0,"ix":6},"o":{"a":0,"k":100,"ix":7},"sk":{"a":0,"k":0,"ix":4},"sa":{"a":0,"k":0,"ix":5},"nm":"Transform"}],"nm":"V","np":3,"cix":2,"bm":0,"ix":2,"mn":"ADBE Vector Group","hd":false},{"ty":"gr","it":[{"ind":0,"ty":"sh","ix":1,"ks":{"a":0,"k":{"i":[[0,0],[0,0],[0,0],[0,0],[0,0],[0,0],[0,0],[0,0],[0,0],[0,0],[0,0],[0,0]],"o":[[0,0],[0,0],[0,0],[0,0],[0,0],[0,0],[0,0],[0,0],[0,0],[0,0],[0,0],[0,0]],"v":[[16.207,0],[19.826,-5.462],[23.412,0],[29.139,0],[22.615,-9.28],[28.591,-17.631],[23.113,-17.631],[19.826,-12.783],[16.705,-17.631],[11.01,-17.631],[17.103,-9.081],[10.745,0]],"c":true},"ix":2},"nm":"x","mn":"ADBE Vector Shape - Group","hd":false},{"ty":"fl","c":{"a":0,"k":[0.678431372549,0.129411764706,0.792156922583,1],"ix":4},"o":{"a":0,"k":100,"ix":5},"r":1,"bm":0,"nm":"Fill 1","mn":"ADBE Vector Graphic - Fill","hd":false},{"ty":"tr","p":{"a":0,"k":[0,0],"ix":2},"a":{"a":0,"k":[0,0],"ix":1},"s":{"a":0,"k":[100,100],"ix":3},"r":{"a":0,"k":0,"ix":6},"o":{"a":0,"k":100,"ix":7},"sk":{"a":0,"k":0,"ix":4},"sa":{"a":0,"k":0,"ix":5},"nm":"Transform"}],"nm":"x","np":3,"cix":2,"bm":0,"ix":3,"mn":"ADBE Vector Group","hd":false}],"ip":91.000003706506,"op":428.000017432797,"st":0,"bm":0},{"ddd":0,"ind":13,"ty":4,"nm":"Vx Outlines","parent":1,"sr":1,"ks":{"o":{"a":1,"k":[{"i":{"x":[0.833],"y":[0.833]},"o":{"x":[0.167],"y":[0.167]},"t":71,"s":[0]},{"i":{"x":[0.833],"y":[0.833]},"o":{"x":[0.167],"y":[0.167]},"t":74,"s":[100]},{"i":{"x":[0.833],"y":[0.833]},"o":{"x":[0.167],"y":[0.167]},"t":420,"s":[100]},{"t":423.000017229143,"s":[0]}],"ix":11},"r":{"a":0,"k":0,"ix":10},"p":{"a":0,"k":[-188.375,191.438,0],"ix":2},"a":{"a":0,"k":[2,-11.5,0],"ix":1},"s":{"a":0,"k":[100,100,100],"ix":6}},"ao":0,"shapes":[{"ty":"gr","it":[{"ind":0,"ty":"sh","ix":1,"ks":{"a":0,"k":{"i":[[0,0],[0,0],[0,0],[0,0],[0,0],[0,0],[0,0]],"o":[[0,0],[0,0],[0,0],[0,0],[0,0],[0,0],[0,0]],"v":[[-3.865,0],[4.851,-24.338],[-0.362,-24.338],[-6.322,-6.325],[-12.481,-24.338],[-17.81,-24.338],[-9.111,0]],"c":true},"ix":2},"nm":"V","mn":"ADBE Vector Shape - Group","hd":false},{"ty":"fl","c":{"a":0,"k":[0.678431372549,0.129411764706,0.792156922583,1],"ix":4},"o":{"a":0,"k":100,"ix":5},"r":1,"bm":0,"nm":"Fill 1","mn":"ADBE Vector Graphic - Fill","hd":false},{"ty":"tr","p":{"a":0,"k":[0,0],"ix":2},"a":{"a":0,"k":[0,0],"ix":1},"s":{"a":0,"k":[100,100],"ix":3},"r":{"a":0,"k":0,"ix":6},"o":{"a":0,"k":100,"ix":7},"sk":{"a":0,"k":0,"ix":4},"sa":{"a":0,"k":0,"ix":5},"nm":"Transform"}],"nm":"V","np":3,"cix":2,"bm":0,"ix":1,"mn":"ADBE Vector Group","hd":false},{"ty":"gr","it":[{"ind":0,"ty":"sh","ix":1,"ks":{"a":0,"k":{"i":[[0,0],[0,0],[0,0],[0,0],[0,0],[0,0],[0,0],[0,0],[0,0],[0,0],[0,0],[0,0]],"o":[[0,0],[0,0],[0,0],[0,0],[0,0],[0,0],[0,0],[0,0],[0,0],[0,0],[0,0],[0,0]],"v":[[10.545,0],[14.165,-5.462],[17.75,0],[23.478,0],[16.954,-9.28],[22.93,-17.631],[17.452,-17.631],[14.165,-12.783],[11.043,-17.631],[5.349,-17.631],[11.442,-9.081],[5.083,0]],"c":true},"ix":2},"nm":"x","mn":"ADBE Vector Shape - Group","hd":false},{"ty":"fl","c":{"a":0,"k":[0.678431372549,0.129411764706,0.792156922583,1],"ix":4},"o":{"a":0,"k":100,"ix":5},"r":1,"bm":0,"nm":"Fill 1","mn":"ADBE Vector Graphic - Fill","hd":false},{"ty":"tr","p":{"a":0,"k":[0,0],"ix":2},"a":{"a":0,"k":[0,0],"ix":1},"s":{"a":0,"k":[100,100],"ix":3},"r":{"a":0,"k":0,"ix":6},"o":{"a":0,"k":100,"ix":7},"sk":{"a":0,"k":0,"ix":4},"sa":{"a":0,"k":0,"ix":5},"nm":"Transform"}],"nm":"x","np":3,"cix":2,"bm":0,"ix":2,"mn":"ADBE Vector Group","hd":false}],"ip":65.0000026475043,"op":428.000017432797,"st":0,"bm":0},{"ddd":0,"ind":14,"ty":4,"nm":"tip 3","parent":1,"sr":1,"ks":{"o":{"a":1,"k":[{"i":{"x":[0.833],"y":[0.833]},"o":{"x":[0.167],"y":[0.167]},"t":420,"s":[100]},{"t":423.000017229143,"s":[0]}],"ix":11},"r":{"a":0,"k":99.061,"ix":10},"p":{"a":1,"k":[{"i":{"x":0.833,"y":0.833},"o":{"x":0.167,"y":0.167},"t":76,"s":[-291.5,-28.25,0],"to":[0,0,0],"ti":[0,0,0]},{"t":95.0000038694293,"s":[-72,-217,0]}],"ix":2},"a":{"a":0,"k":[-280.5,-20,0],"ix":1},"s":{"a":0,"k":[100,100,100],"ix":6}},"ao":0,"shapes":[{"ty":"gr","it":[{"ind":0,"ty":"sh","ix":1,"ks":{"a":0,"k":{"i":[[0,0],[0,0],[0,0]],"o":[[0,0],[0,0],[0,0]],"v":[[-295,-33],[-289.5,-8.5],[-271,-30]],"c":true},"ix":2},"nm":"Path 1","mn":"ADBE Vector Shape - Group","hd":false},{"ty":"fl","c":{"a":0,"k":[0.129411764706,0.792156922583,0.658823529412,1],"ix":4},"o":{"a":0,"k":100,"ix":5},"r":1,"bm":0,"nm":"Fill 1","mn":"ADBE Vector Graphic - Fill","hd":false},{"ty":"tr","p":{"a":0,"k":[0,0],"ix":2},"a":{"a":0,"k":[0,0],"ix":1},"s":{"a":0,"k":[100,100],"ix":3},"r":{"a":0,"k":0,"ix":6},"o":{"a":0,"k":100,"ix":7},"sk":{"a":0,"k":0,"ix":4},"sa":{"a":0,"k":0,"ix":5},"nm":"Transform"}],"nm":"Shape 1","np":3,"cix":2,"bm":0,"ix":1,"mn":"ADBE Vector Group","hd":false}],"ip":76.0000030955435,"op":428.000017432797,"st":0,"bm":0},{"ddd":0,"ind":15,"ty":4,"nm":"tip","parent":1,"sr":1,"ks":{"o":{"a":1,"k":[{"i":{"x":[0.833],"y":[0.833]},"o":{"x":[0.167],"y":[0.167]},"t":420,"s":[100]},{"t":423.000017229143,"s":[0]}],"ix":11},"r":{"a":0,"k":0,"ix":10},"p":{"a":1,"k":[{"i":{"x":0.833,"y":0.833},"o":{"x":0.167,"y":0.167},"t":50,"s":[-64.5,167.75,0],"to":[0,0,0],"ti":[0,0,0]},{"t":72.0000029326201,"s":[-280,-19,0]}],"ix":2},"a":{"a":0,"k":[-280.5,-20,0],"ix":1},"s":{"a":0,"k":[100,100,100],"ix":6}},"ao":0,"shapes":[{"ty":"gr","it":[{"ind":0,"ty":"sh","ix":1,"ks":{"a":0,"k":{"i":[[0,0],[0,0],[0,0]],"o":[[0,0],[0,0],[0,0]],"v":[[-295,-33],[-289.5,-8.5],[-271,-30]],"c":true},"ix":2},"nm":"Path 1","mn":"ADBE Vector Shape - Group","hd":false},{"ty":"fl","c":{"a":0,"k":[0.129411764706,0.792156922583,0.658823529412,1],"ix":4},"o":{"a":0,"k":100,"ix":5},"r":1,"bm":0,"nm":"Fill 1","mn":"ADBE Vector Graphic - Fill","hd":false},{"ty":"tr","p":{"a":0,"k":[0,0],"ix":2},"a":{"a":0,"k":[0,0],"ix":1},"s":{"a":0,"k":[100,100],"ix":3},"r":{"a":0,"k":0,"ix":6},"o":{"a":0,"k":100,"ix":7},"sk":{"a":0,"k":0,"ix":4},"sa":{"a":0,"k":0,"ix":5},"nm":"Transform"}],"nm":"Shape 1","np":3,"cix":2,"bm":0,"ix":1,"mn":"ADBE Vector Group","hd":false}],"ip":50.0000020365418,"op":428.000017432797,"st":0,"bm":0},{"ddd":0,"ind":16,"ty":4,"nm":"arrow 2","parent":1,"sr":1,"ks":{"o":{"a":1,"k":[{"i":{"x":[0.833],"y":[0.833]},"o":{"x":[0.167],"y":[0.167]},"t":420,"s":[100]},{"t":423.000017229143,"s":[0]}],"ix":11},"r":{"a":0,"k":98.605,"ix":10},"p":{"a":0,"k":[-290,-28,0],"ix":2},"a":{"a":0,"k":[-55,171,0],"ix":1},"s":{"a":0,"k":[100,100,100],"ix":6}},"ao":0,"shapes":[{"ty":"gr","it":[{"ind":0,"ty":"sh","ix":1,"ks":{"a":0,"k":{"i":[[0,0],[0,0]],"o":[[0,0],[0,0]],"v":[[-55,172],[-282,-24]],"c":false},"ix":2},"nm":"Path 1","mn":"ADBE Vector Shape - Group","hd":false},{"ty":"tm","s":{"a":1,"k":[{"i":{"x":[0.833],"y":[0.833]},"o":{"x":[0.167],"y":[0.167]},"t":76,"s":[0]},{"t":95.0000038694293,"s":[0]}],"ix":1},"e":{"a":1,"k":[{"i":{"x":[0.833],"y":[0.833]},"o":{"x":[0.167],"y":[0.167]},"t":76,"s":[0]},{"t":95.0000038694293,"s":[100]}],"ix":2},"o":{"a":0,"k":0,"ix":3},"m":1,"ix":2,"nm":"Trim Paths 1","mn":"ADBE Vector Filter - Trim","hd":false},{"ty":"st","c":{"a":0,"k":[0.129411764706,0.792156922583,0.658823529412,1],"ix":3},"o":{"a":0,"k":100,"ix":4},"w":{"a":0,"k":6,"ix":5},"lc":1,"lj":1,"ml":4,"bm":0,"nm":"Stroke 1","mn":"ADBE Vector Graphic - Stroke","hd":false},{"ty":"fl","c":{"a":0,"k":[0.917646998985,0.074509998396,0.074509998396,1],"ix":4},"o":{"a":0,"k":100,"ix":5},"r":1,"bm":0,"nm":"Fill 1","mn":"ADBE Vector Graphic - Fill","hd":false},{"ty":"tr","p":{"a":0,"k":[0,0],"ix":2},"a":{"a":0,"k":[0,0],"ix":1},"s":{"a":0,"k":[100,100],"ix":3},"r":{"a":0,"k":0,"ix":6},"o":{"a":0,"k":100,"ix":7},"sk":{"a":0,"k":0,"ix":4},"sa":{"a":0,"k":0,"ix":5},"nm":"Transform"}],"nm":"Shape 1","np":4,"cix":2,"bm":0,"ix":1,"mn":"ADBE Vector Group","hd":false}],"ip":0,"op":428.000017432797,"st":0,"bm":0},{"ddd":0,"ind":17,"ty":4,"nm":"arrow","parent":1,"sr":1,"ks":{"o":{"a":1,"k":[{"i":{"x":[0.833],"y":[0.833]},"o":{"x":[0.167],"y":[0.167]},"t":420,"s":[100]},{"t":423.000017229143,"s":[0]}],"ix":11},"r":{"a":0,"k":0,"ix":10},"p":{"a":0,"k":[-65.75,166,0],"ix":2},"a":{"a":0,"k":[-54.75,172,0],"ix":1},"s":{"a":0,"k":[100,100,100],"ix":6}},"ao":0,"shapes":[{"ty":"gr","it":[{"ind":0,"ty":"sh","ix":1,"ks":{"a":0,"k":{"i":[[0,0],[0,0]],"o":[[0,0],[0,0]],"v":[[-53.25,173.75],[-277.5,-20.5]],"c":false},"ix":2},"nm":"Path 1","mn":"ADBE Vector Shape - Group","hd":false},{"ty":"tm","s":{"a":1,"k":[{"i":{"x":[0.833],"y":[0.833]},"o":{"x":[0.167],"y":[0.167]},"t":50,"s":[0]},{"t":72.0000029326201,"s":[0]}],"ix":1},"e":{"a":1,"k":[{"i":{"x":[0.833],"y":[0.833]},"o":{"x":[0.167],"y":[0.167]},"t":50,"s":[0]},{"t":72.0000029326201,"s":[100]}],"ix":2},"o":{"a":0,"k":0,"ix":3},"m":1,"ix":2,"nm":"Trim Paths 1","mn":"ADBE Vector Filter - Trim","hd":false},{"ty":"st","c":{"a":0,"k":[0.129801282696,0.791835171569,0.659245928596,1],"ix":3},"o":{"a":0,"k":100,"ix":4},"w":{"a":0,"k":6,"ix":5},"lc":1,"lj":1,"ml":4,"bm":0,"nm":"Stroke 1","mn":"ADBE Vector Graphic - Stroke","hd":false},{"ty":"fl","c":{"a":0,"k":[0.917646998985,0.074509998396,0.074509998396,1],"ix":4},"o":{"a":0,"k":100,"ix":5},"r":1,"bm":0,"nm":"Fill 1","mn":"ADBE Vector Graphic - Fill","hd":false},{"ty":"tr","p":{"a":0,"k":[0,0],"ix":2},"a":{"a":0,"k":[0,0],"ix":1},"s":{"a":0,"k":[100,100],"ix":3},"r":{"a":0,"k":0,"ix":6},"o":{"a":0,"k":100,"ix":7},"sk":{"a":0,"k":0,"ix":4},"sa":{"a":0,"k":0,"ix":5},"nm":"Transform"}],"nm":"Shape 1","np":4,"cix":2,"bm":0,"ix":1,"mn":"ADBE Vector Group","hd":false}],"ip":50.0000020365418,"op":428.000017432797,"st":0,"bm":0},{"ddd":0,"ind":18,"ty":4,"nm":"Ball 2","parent":1,"sr":1,"ks":{"o":{"a":1,"k":[{"i":{"x":[0.833],"y":[0.833]},"o":{"x":[0.167],"y":[0.167]},"t":72,"s":[45]},{"i":{"x":[0.833],"y":[0.833]},"o":{"x":[0.167],"y":[0.167]},"t":420,"s":[45]},{"t":423.000017229143,"s":[0]}],"ix":11},"r":{"a":0,"k":0,"ix":10},"p":{"a":1,"k":[{"i":{"x":0.833,"y":0.833},"o":{"x":0.167,"y":0.167},"t":50,"s":[-66.601,166.455,0],"to":[0,0,0],"ti":[0,0,0]},{"t":69.0000028104276,"s":[-290.601,-27.545,0]}],"ix":2},"a":{"a":0,"k":[100.621,29.379,0],"ix":1},"s":{"a":0,"k":[122.982,122.982,100],"ix":6}},"ao":0,"shapes":[{"ty":"gr","it":[{"d":1,"ty":"el","s":{"a":0,"k":[42.758,42.758],"ix":2},"p":{"a":0,"k":[0,0],"ix":3},"nm":"Ellipse Path 1","mn":"ADBE Vector Shape - Ellipse","hd":false},{"ty":"gf","o":{"a":0,"k":100,"ix":10},"r":1,"bm":0,"g":{"p":3,"k":{"a":0,"k":[0,0.93,0.774,0.774,0.374,0.551,0.522,0.758,1,0.171,0.271,0.742],"ix":9}},"s":{"a":0,"k":[-0.887,-4.633],"ix":5},"e":{"a":0,"k":[25.867,3.754],"ix":6},"t":2,"h":{"a":0,"k":0,"ix":7},"a":{"a":0,"k":0,"ix":8},"nm":"Gradient Fill 1","mn":"ADBE Vector Graphic - G-Fill","hd":false},{"ty":"tr","p":{"a":0,"k":[100.621,29.379],"ix":2},"a":{"a":0,"k":[0,0],"ix":1},"s":{"a":0,"k":[100,100],"ix":3},"r":{"a":0,"k":0,"ix":6},"o":{"a":0,"k":100,"ix":7},"sk":{"a":0,"k":0,"ix":4},"sa":{"a":0,"k":0,"ix":5},"nm":"Transform"}],"nm":"Ellipse 1","np":3,"cix":2,"bm":0,"ix":1,"mn":"ADBE Vector Group","hd":false}],"ip":72.0000029326201,"op":428.000017432797,"st":0,"bm":0},{"ddd":0,"ind":19,"ty":4,"nm":"Ball 3","parent":1,"sr":1,"ks":{"o":{"a":1,"k":[{"i":{"x":[0.833],"y":[0.833]},"o":{"x":[0.167],"y":[0.167]},"t":50,"s":[45]},{"i":{"x":[0.833],"y":[0.833]},"o":{"x":[0.167],"y":[0.167]},"t":420,"s":[45]},{"t":423.000017229143,"s":[0]}],"ix":11},"r":{"a":0,"k":0,"ix":10},"p":{"a":0,"k":[-66.601,166.455,0],"ix":2},"a":{"a":0,"k":[100.621,29.379,0],"ix":1},"s":{"a":0,"k":[122.982,122.982,100],"ix":6}},"ao":0,"shapes":[{"ty":"gr","it":[{"d":1,"ty":"el","s":{"a":0,"k":[42.758,42.758],"ix":2},"p":{"a":0,"k":[0,0],"ix":3},"nm":"Ellipse Path 1","mn":"ADBE Vector Shape - Ellipse","hd":false},{"ty":"gf","o":{"a":0,"k":100,"ix":10},"r":1,"bm":0,"g":{"p":3,"k":{"a":0,"k":[0,0.93,0.774,0.774,0.374,0.551,0.522,0.758,1,0.171,0.271,0.742],"ix":9}},"s":{"a":0,"k":[-0.887,-4.633],"ix":5},"e":{"a":0,"k":[25.867,3.754],"ix":6},"t":2,"h":{"a":0,"k":0,"ix":7},"a":{"a":0,"k":0,"ix":8},"nm":"Gradient Fill 1","mn":"ADBE Vector Graphic - G-Fill","hd":false},{"ty":"tr","p":{"a":0,"k":[100.621,29.379],"ix":2},"a":{"a":0,"k":[0,0],"ix":1},"s":{"a":0,"k":[100,100],"ix":3},"r":{"a":0,"k":0,"ix":6},"o":{"a":0,"k":100,"ix":7},"sk":{"a":0,"k":0,"ix":4},"sa":{"a":0,"k":0,"ix":5},"nm":"Transform"}],"nm":"Ellipse 1","np":3,"cix":2,"bm":0,"ix":1,"mn":"ADBE Vector Group","hd":false}],"ip":47.0000019143492,"op":428.000017432797,"st":0,"bm":0},{"ddd":0,"ind":20,"ty":4,"nm":"Ball","parent":1,"sr":1,"ks":{"o":{"a":1,"k":[{"i":{"x":[0.833],"y":[0.833]},"o":{"x":[0.167],"y":[0.167]},"t":420,"s":[100]},{"t":423.000017229143,"s":[0]}],"ix":11},"r":{"a":0,"k":0,"ix":10},"p":{"a":1,"k":[{"i":{"x":0.833,"y":0.833},"o":{"x":0.167,"y":0.167},"t":50,"s":[-66.601,166.455,0],"to":[0,0,0],"ti":[0,0,0]},{"i":{"x":0.833,"y":0.833},"o":{"x":0.167,"y":0.167},"t":72,"s":[-290.601,-27.545,0],"to":[0,0,0],"ti":[0,0,0]},{"i":{"x":0.833,"y":0.833},"o":{"x":0.167,"y":0.167},"t":75,"s":[-290.601,-27.545,0],"to":[0,0,0],"ti":[0,0,0]},{"t":95.0000038694293,"s":[-65.601,-222.545,0]}],"ix":2},"a":{"a":0,"k":[100.621,29.379,0],"ix":1},"s":{"a":0,"k":[122.982,122.982,100],"ix":6}},"ao":0,"shapes":[{"ty":"gr","it":[{"d":1,"ty":"el","s":{"a":0,"k":[42.758,42.758],"ix":2},"p":{"a":0,"k":[0,0],"ix":3},"nm":"Ellipse Path 1","mn":"ADBE Vector Shape - Ellipse","hd":false},{"ty":"gf","o":{"a":0,"k":100,"ix":10},"r":1,"bm":0,"g":{"p":3,"k":{"a":0,"k":[0,0.93,0.774,0.774,0.374,0.551,0.522,0.758,1,0.171,0.271,0.742],"ix":9}},"s":{"a":0,"k":[-0.887,-4.633],"ix":5},"e":{"a":0,"k":[25.867,3.754],"ix":6},"t":2,"h":{"a":0,"k":0,"ix":7},"a":{"a":0,"k":0,"ix":8},"nm":"Gradient Fill 1","mn":"ADBE Vector Graphic - G-Fill","hd":false},{"ty":"tr","p":{"a":0,"k":[100.621,29.379],"ix":2},"a":{"a":0,"k":[0,0],"ix":1},"s":{"a":0,"k":[100,100],"ix":3},"r":{"a":0,"k":0,"ix":6},"o":{"a":0,"k":100,"ix":7},"sk":{"a":0,"k":0,"ix":4},"sa":{"a":0,"k":0,"ix":5},"nm":"Transform"}],"nm":"Ellipse 1","np":3,"cix":2,"bm":0,"ix":1,"mn":"ADBE Vector Group","hd":false}],"ip":47.0000019143492,"op":428.000017432797,"st":0,"bm":0},{"ddd":0,"ind":21,"ty":4,"nm":"tip 5","parent":1,"sr":1,"ks":{"o":{"a":1,"k":[{"i":{"x":[0.833],"y":[0.833]},"o":{"x":[0.167],"y":[0.167]},"t":420,"s":[100]},{"t":423.000017229143,"s":[0]}],"ix":11},"r":{"a":0,"k":-219.177,"ix":10},"p":{"a":1,"k":[{"i":{"x":0.833,"y":0.833},"o":{"x":0.167,"y":0.167},"t":76,"s":[-299,-30.25,0],"to":[0,0,0],"ti":[0,0,0]},{"t":95.0000038694293,"s":[-83.5,-29,0]}],"ix":2},"a":{"a":0,"k":[-280.5,-20,0],"ix":1},"s":{"a":0,"k":[100,100,100],"ix":6}},"ao":0,"shapes":[{"ty":"gr","it":[{"ind":0,"ty":"sh","ix":1,"ks":{"a":0,"k":{"i":[[0,0],[0,0],[0,0]],"o":[[0,0],[0,0],[0,0]],"v":[[-295,-33],[-289.5,-8.5],[-271,-30]],"c":true},"ix":2},"nm":"Path 1","mn":"ADBE Vector Shape - Group","hd":false},{"ty":"fl","c":{"a":0,"k":[0.678431372549,0.129411764706,0.792156922583,1],"ix":4},"o":{"a":0,"k":100,"ix":5},"r":1,"bm":0,"nm":"Fill 1","mn":"ADBE Vector Graphic - Fill","hd":false},{"ty":"tr","p":{"a":0,"k":[0,0],"ix":2},"a":{"a":0,"k":[0,0],"ix":1},"s":{"a":0,"k":[100,100],"ix":3},"r":{"a":0,"k":0,"ix":6},"o":{"a":0,"k":100,"ix":7},"sk":{"a":0,"k":0,"ix":4},"sa":{"a":0,"k":0,"ix":5},"nm":"Transform"}],"nm":"Shape 1","np":3,"cix":2,"bm":0,"ix":1,"mn":"ADBE Vector Group","hd":false}],"ip":76.0000030955435,"op":428.000017432797,"st":4.00000016292334,"bm":0},{"ddd":0,"ind":22,"ty":4,"nm":"tip 4","parent":1,"sr":1,"ks":{"o":{"a":1,"k":[{"i":{"x":[0.833],"y":[0.833]},"o":{"x":[0.167],"y":[0.167]},"t":420,"s":[100]},{"t":423.000017229143,"s":[0]}],"ix":11},"r":{"a":0,"k":-41.107,"ix":10},"p":{"a":1,"k":[{"i":{"x":0.833,"y":0.833},"o":{"x":0.167,"y":0.167},"t":50,"s":[-67.5,166.75,0],"to":[0,0,0],"ti":[0,0,0]},{"t":72.0000029326201,"s":[-297,167,0]}],"ix":2},"a":{"a":0,"k":[-280.5,-20,0],"ix":1},"s":{"a":0,"k":[100,100,100],"ix":6}},"ao":0,"shapes":[{"ty":"gr","it":[{"ind":0,"ty":"sh","ix":1,"ks":{"a":0,"k":{"i":[[0,0],[0,0],[0,0]],"o":[[0,0],[0,0],[0,0]],"v":[[-295,-33],[-289.5,-8.5],[-271,-30]],"c":true},"ix":2},"nm":"Path 1","mn":"ADBE Vector Shape - Group","hd":false},{"ty":"fl","c":{"a":0,"k":[0.678431372549,0.129411764706,0.792156922583,1],"ix":4},"o":{"a":0,"k":100,"ix":5},"r":1,"bm":0,"nm":"Fill 1","mn":"ADBE Vector Graphic - Fill","hd":false},{"ty":"tr","p":{"a":0,"k":[0,0],"ix":2},"a":{"a":0,"k":[0,0],"ix":1},"s":{"a":0,"k":[100,100],"ix":3},"r":{"a":0,"k":0,"ix":6},"o":{"a":0,"k":100,"ix":7},"sk":{"a":0,"k":0,"ix":4},"sa":{"a":0,"k":0,"ix":5},"nm":"Transform"}],"nm":"Shape 1","np":3,"cix":2,"bm":0,"ix":1,"mn":"ADBE Vector Group","hd":false}],"ip":50.0000020365418,"op":428.000017432797,"st":0,"bm":0},{"ddd":0,"ind":23,"ty":4,"nm":"arrow 3","parent":1,"sr":1,"ks":{"o":{"a":1,"k":[{"i":{"x":[0.833],"y":[0.833]},"o":{"x":[0.167],"y":[0.167]},"t":420,"s":[100]},{"t":423.000017229143,"s":[0]}],"ix":11},"r":{"a":0,"k":180.159,"ix":10},"p":{"a":0,"k":[-293.5,-28.5,0],"ix":2},"a":{"a":0,"k":[-66,166,0],"ix":1},"s":{"a":0,"k":[100,100,100],"ix":6}},"ao":0,"shapes":[{"ty":"gr","it":[{"ind":0,"ty":"sh","ix":1,"ks":{"a":0,"k":{"i":[[0,0],[0,0]],"o":[[0,0],[0,0]],"v":[[-67,167],[-283.999,167.453]],"c":false},"ix":2},"nm":"Path 1","mn":"ADBE Vector Shape - Group","hd":false},{"ty":"st","c":{"a":0,"k":[0.680075013404,0.129411764706,0.792156922583,1],"ix":3},"o":{"a":0,"k":100,"ix":4},"w":{"a":0,"k":6,"ix":5},"lc":1,"lj":1,"ml":4,"bm":0,"nm":"Stroke 1","mn":"ADBE Vector Graphic - Stroke","hd":false},{"ty":"fl","c":{"a":0,"k":[0.129411764706,0.792156922583,0.658823529412,1],"ix":4},"o":{"a":0,"k":100,"ix":5},"r":1,"bm":0,"nm":"Fill 1","mn":"ADBE Vector Graphic - Fill","hd":false},{"ty":"tr","p":{"a":0,"k":[0,0],"ix":2},"a":{"a":0,"k":[0,0],"ix":1},"s":{"a":0,"k":[100,100],"ix":3},"r":{"a":0,"k":0,"ix":6},"o":{"a":0,"k":100,"ix":7},"sk":{"a":0,"k":0,"ix":4},"sa":{"a":0,"k":0,"ix":5},"nm":"Transform"}],"nm":"Shape 1","np":3,"cix":2,"bm":0,"ix":1,"mn":"ADBE Vector Group","hd":false},{"ty":"tm","s":{"a":1,"k":[{"i":{"x":[0.833],"y":[0.833]},"o":{"x":[0.167],"y":[0.167]},"t":75,"s":[0]},{"t":95.0000038694293,"s":[0]}],"ix":1},"e":{"a":1,"k":[{"i":{"x":[0.833],"y":[0.833]},"o":{"x":[0.167],"y":[0.167]},"t":75,"s":[0]},{"t":95.0000038694293,"s":[100]}],"ix":2},"o":{"a":0,"k":0,"ix":3},"m":1,"ix":2,"nm":"Trim Paths 1","mn":"ADBE Vector Filter - Trim","hd":false}],"ip":75.0000030548126,"op":428.000017432797,"st":25.0000010182709,"bm":0},{"ddd":0,"ind":24,"ty":4,"nm":"arrow","parent":1,"sr":1,"ks":{"o":{"a":1,"k":[{"i":{"x":[0.833],"y":[0.833]},"o":{"x":[0.167],"y":[0.167]},"t":420,"s":[100]},{"t":423.000017229143,"s":[0]}],"ix":11},"r":{"a":0,"k":0,"ix":10},"p":{"a":0,"k":[-67,166,0],"ix":2},"a":{"a":0,"k":[-66,166,0],"ix":1},"s":{"a":0,"k":[100,100,100],"ix":6}},"ao":0,"shapes":[{"ty":"gr","it":[{"ind":0,"ty":"sh","ix":1,"ks":{"a":0,"k":{"i":[[0,0],[0,0]],"o":[[0,0],[0,0]],"v":[[-67,167],[-301,167]],"c":false},"ix":2},"nm":"Path 1","mn":"ADBE Vector Shape - Group","hd":false},{"ty":"st","c":{"a":0,"k":[0.680075013404,0.129411764706,0.792156922583,1],"ix":3},"o":{"a":0,"k":100,"ix":4},"w":{"a":0,"k":6,"ix":5},"lc":1,"lj":1,"ml":4,"bm":0,"nm":"Stroke 1","mn":"ADBE Vector Graphic - Stroke","hd":false},{"ty":"fl","c":{"a":0,"k":[0.129411764706,0.792156922583,0.658823529412,1],"ix":4},"o":{"a":0,"k":100,"ix":5},"r":1,"bm":0,"nm":"Fill 1","mn":"ADBE Vector Graphic - Fill","hd":false},{"ty":"tr","p":{"a":0,"k":[0,0],"ix":2},"a":{"a":0,"k":[0,0],"ix":1},"s":{"a":0,"k":[100,100],"ix":3},"r":{"a":0,"k":0,"ix":6},"o":{"a":0,"k":100,"ix":7},"sk":{"a":0,"k":0,"ix":4},"sa":{"a":0,"k":0,"ix":5},"nm":"Transform"}],"nm":"Shape 1","np":3,"cix":2,"bm":0,"ix":1,"mn":"ADBE Vector Group","hd":false},{"ty":"tm","s":{"a":1,"k":[{"i":{"x":[0.833],"y":[0.833]},"o":{"x":[0.167],"y":[0.167]},"t":50,"s":[0]},{"t":72.0000029326201,"s":[0]}],"ix":1},"e":{"a":1,"k":[{"i":{"x":[0.833],"y":[0.833]},"o":{"x":[0.167],"y":[0.167]},"t":50,"s":[0]},{"t":72.0000029326201,"s":[100]}],"ix":2},"o":{"a":0,"k":0,"ix":3},"m":1,"ix":2,"nm":"Trim Paths 1","mn":"ADBE Vector Filter - Trim","hd":false}],"ip":50.0000020365418,"op":428.000017432797,"st":0,"bm":0},{"ddd":0,"ind":25,"ty":4,"nm":"Shape Layer 6","parent":1,"sr":1,"ks":{"o":{"a":1,"k":[{"i":{"x":[0.833],"y":[0.833]},"o":{"x":[0.167],"y":[0.167]},"t":4,"s":[0]},{"i":{"x":[0.833],"y":[0.833]},"o":{"x":[0.167],"y":[0.167]},"t":8,"s":[100]},{"i":{"x":[0.833],"y":[0.833]},"o":{"x":[0.167],"y":[0.167]},"t":420,"s":[100]},{"t":423.000017229143,"s":[0]}],"ix":11},"r":{"a":0,"k":0,"ix":10},"p":{"a":0,"k":[280.46,-196.35,0],"ix":2},"a":{"a":0,"k":[180,-263,0],"ix":1},"s":{"a":0,"k":[119,119,100],"ix":6}},"ao":0,"shapes":[{"ty":"gr","it":[{"ind":0,"ty":"sh","ix":1,"ks":{"a":1,"k":[{"i":{"x":0.833,"y":0.833},"o":{"x":0.167,"y":0.167},"t":18,"s":[{"i":[[0,0],[0,0]],"o":[[0,0],[0,0]],"v":[[64,-347],[372.5,-393]],"c":false}]},{"i":{"x":0.833,"y":0.833},"o":{"x":0.167,"y":0.167},"t":28,"s":[{"i":[[0,0],[0,0]],"o":[[0,0],[0,0]],"v":[[94,-339],[308.5,-381]],"c":false}]},{"i":{"x":0.833,"y":0.833},"o":{"x":0.167,"y":0.167},"t":38,"s":[{"i":[[0,0],[0,0]],"o":[[0,0],[0,0]],"v":[[125,-329],[245.5,-373]],"c":false}]},{"i":{"x":0.833,"y":0.833},"o":{"x":0.167,"y":0.167},"t":42,"s":[{"i":[[0,0],[0,0]],"o":[[0,0],[0,0]],"v":[[136,-324],[217.5,-367]],"c":false}]},{"t":44.0000017921567,"s":[{"i":[[0,0],[0,0]],"o":[[0,0],[0,0]],"v":[[145,-325],[206.5,-367]],"c":false}]}],"ix":2},"nm":"Path 1","mn":"ADBE Vector Shape - Group","hd":false},{"ty":"st","c":{"a":0,"k":[0,0,0,1],"ix":3},"o":{"a":0,"k":100,"ix":4},"w":{"a":0,"k":6,"ix":5},"lc":1,"lj":1,"ml":4,"bm":0,"nm":"Stroke 1","mn":"ADBE Vector Graphic - Stroke","hd":false},{"ty":"tr","p":{"a":0,"k":[0,0],"ix":2},"a":{"a":0,"k":[0,0],"ix":1},"s":{"a":0,"k":[100,100],"ix":3},"r":{"a":0,"k":0,"ix":6},"o":{"a":0,"k":100,"ix":7},"sk":{"a":0,"k":0,"ix":4},"sa":{"a":0,"k":0,"ix":5},"nm":"Transform"}],"nm":"Shape 1","np":3,"cix":2,"bm":0,"ix":1,"mn":"ADBE Vector Group","hd":false},{"ty":"gr","it":[{"ind":0,"ty":"sh","ix":1,"ks":{"a":1,"k":[{"i":{"x":0.833,"y":0.833},"o":{"x":0.167,"y":0.167},"t":18,"s":[{"i":[[0,0],[0,0]],"o":[[0,0],[0,0]],"v":[[-391.5,-347.5],[-211,-394]],"c":false}]},{"i":{"x":0.833,"y":0.833},"o":{"x":0.167,"y":0.167},"t":28,"s":[{"i":[[0,0],[0,0]],"o":[[0,0],[0,0]],"v":[[-341.5,-338.5],[-255,-384]],"c":false}]},{"i":{"x":0.833,"y":0.833},"o":{"x":0.167,"y":0.167},"t":33,"s":[{"i":[[0,0],[0,0]],"o":[[0,0],[0,0]],"v":[[-319.5,-335.5],[-275,-380]],"c":false}]},{"i":{"x":0.833,"y":0.833},"o":{"x":0.167,"y":0.167},"t":35,"s":[{"i":[[0,0],[0,0]],"o":[[0,0],[0,0]],"v":[[-308.5,-332.5],[-286,-377]],"c":false}]},{"i":{"x":0.833,"y":0.833},"o":{"x":0.167,"y":0.167},"t":38,"s":[{"i":[[0,0],[0,0]],"o":[[0,0],[0,0]],"v":[[-294.5,-327.5],[-299,-374]],"c":false}]},{"i":{"x":0.833,"y":0.833},"o":{"x":0.167,"y":0.167},"t":42,"s":[{"i":[[0,0],[0,0]],"o":[[0,0],[0,0]],"v":[[-274.5,-325.5],[-315,-369]],"c":false}]},{"t":44.0000017921567,"s":[{"i":[[0,0],[0,0]],"o":[[0,0],[0,0]],"v":[[-263.5,-322.5],[-324,-366]],"c":false}]}],"ix":2},"nm":"Path 1","mn":"ADBE Vector Shape - Group","hd":false},{"ty":"st","c":{"a":0,"k":[0,0,0,1],"ix":3},"o":{"a":0,"k":100,"ix":4},"w":{"a":0,"k":6,"ix":5},"lc":1,"lj":1,"ml":4,"bm":0,"nm":"Stroke 1","mn":"ADBE Vector Graphic - Stroke","hd":false},{"ty":"tr","p":{"a":0,"k":[0,0],"ix":2},"a":{"a":0,"k":[0,0],"ix":1},"s":{"a":0,"k":[100,100],"ix":3},"r":{"a":0,"k":0,"ix":6},"o":{"a":0,"k":100,"ix":7},"sk":{"a":0,"k":0,"ix":4},"sa":{"a":0,"k":0,"ix":5},"nm":"Transform"}],"nm":"Shape 2","np":3,"cix":2,"bm":0,"ix":2,"mn":"ADBE Vector Group","hd":false},{"ty":"gr","it":[{"ind":0,"ty":"sh","ix":1,"ks":{"a":1,"k":[{"i":{"x":0.833,"y":0.833},"o":{"x":0.167,"y":0.167},"t":18,"s":[{"i":[[0,0],[0,0]],"o":[[0,0],[0,0]],"v":[[62,104],[374,188]],"c":false}]},{"i":{"x":0.833,"y":0.833},"o":{"x":0.167,"y":0.167},"t":28,"s":[{"i":[[0,0],[0,0]],"o":[[0,0],[0,0]],"v":[[94,98],[312,178]],"c":false}]},{"i":{"x":0.833,"y":0.833},"o":{"x":0.167,"y":0.167},"t":33,"s":[{"i":[[0,0],[0,0]],"o":[[0,0],[0,0]],"v":[[108,94],[277,173]],"c":false}]},{"i":{"x":0.833,"y":0.833},"o":{"x":0.167,"y":0.167},"t":36,"s":[{"i":[[0,0],[0,0]],"o":[[0,0],[0,0]],"v":[[119,92],[258,171]],"c":false}]},{"i":{"x":0.833,"y":0.833},"o":{"x":0.167,"y":0.167},"t":38,"s":[{"i":[[0,0],[0,0]],"o":[[0,0],[0,0]],"v":[[125,90],[244,168]],"c":false}]},{"i":{"x":0.833,"y":0.833},"o":{"x":0.167,"y":0.167},"t":42,"s":[{"i":[[0,0],[0,0]],"o":[[0,0],[0,0]],"v":[[137,86],[220,166]],"c":false}]},{"t":44.0000017921567,"s":[{"i":[[0,0],[0,0]],"o":[[0,0],[0,0]],"v":[[144,86],[206,163]],"c":false}]}],"ix":2},"nm":"Path 1","mn":"ADBE Vector Shape - Group","hd":false},{"ty":"st","c":{"a":0,"k":[0,0,0,1],"ix":3},"o":{"a":0,"k":100,"ix":4},"w":{"a":0,"k":6,"ix":5},"lc":1,"lj":1,"ml":4,"bm":0,"nm":"Stroke 1","mn":"ADBE Vector Graphic - Stroke","hd":false},{"ty":"tr","p":{"a":0,"k":[0,0],"ix":2},"a":{"a":0,"k":[0,0],"ix":1},"s":{"a":0,"k":[100,100],"ix":3},"r":{"a":0,"k":0,"ix":6},"o":{"a":0,"k":100,"ix":7},"sk":{"a":0,"k":0,"ix":4},"sa":{"a":0,"k":0,"ix":5},"nm":"Transform"}],"nm":"Shape 3","np":3,"cix":2,"bm":0,"ix":3,"mn":"ADBE Vector Group","hd":false},{"ty":"gr","it":[{"ind":0,"ty":"sh","ix":1,"ks":{"a":1,"k":[{"i":{"x":0.833,"y":0.833},"o":{"x":0.167,"y":0.167},"t":18,"s":[{"i":[[0,0],[0,0]],"o":[[0,0],[0,0]],"v":[[-392,108.5],[-211.75,190]],"c":false}]},{"i":{"x":0.833,"y":0.833},"o":{"x":0.167,"y":0.167},"t":28,"s":[{"i":[[0,0],[0,0]],"o":[[0,0],[0,0]],"v":[[-343,99],[-255.25,180.5]],"c":false}]},{"i":{"x":0.833,"y":0.833},"o":{"x":0.167,"y":0.167},"t":31,"s":[{"i":[[0,0],[0,0]],"o":[[0,0],[0,0]],"v":[[-328,96.5],[-268.25,178]],"c":false}]},{"i":{"x":0.833,"y":0.833},"o":{"x":0.167,"y":0.167},"t":33,"s":[{"i":[[0,0],[0,0]],"o":[[0,0],[0,0]],"v":[[-318.5,94.5],[-277.25,176.5]],"c":false}]},{"i":{"x":0.833,"y":0.833},"o":{"x":0.167,"y":0.167},"t":35,"s":[{"i":[[0,0],[0,0]],"o":[[0,0],[0,0]],"v":[[-309,92],[-286.75,175]],"c":false}]},{"i":{"x":0.833,"y":0.833},"o":{"x":0.167,"y":0.167},"t":38,"s":[{"i":[[0,0],[0,0]],"o":[[0,0],[0,0]],"v":[[-295,90],[-298.75,171]],"c":false}]},{"i":{"x":0.833,"y":0.833},"o":{"x":0.167,"y":0.167},"t":42,"s":[{"i":[[0,0],[0,0]],"o":[[0,0],[0,0]],"v":[[-273,86],[-314.75,165]],"c":false}]},{"t":44.0000017921567,"s":[{"i":[[0,0],[0,0]],"o":[[0,0],[0,0]],"v":[[-265,85],[-322.75,163]],"c":false}]}],"ix":2},"nm":"Path 1","mn":"ADBE Vector Shape - Group","hd":false},{"ty":"st","c":{"a":0,"k":[0,0,0,1],"ix":3},"o":{"a":0,"k":100,"ix":4},"w":{"a":0,"k":6,"ix":5},"lc":1,"lj":1,"ml":4,"bm":0,"nm":"Stroke 1","mn":"ADBE Vector Graphic - Stroke","hd":false},{"ty":"tr","p":{"a":0,"k":[0,0],"ix":2},"a":{"a":0,"k":[0,0],"ix":1},"s":{"a":0,"k":[100,100],"ix":3},"r":{"a":0,"k":0,"ix":6},"o":{"a":0,"k":100,"ix":7},"sk":{"a":0,"k":0,"ix":4},"sa":{"a":0,"k":0,"ix":5},"nm":"Transform"}],"nm":"Shape 4","np":3,"cix":2,"bm":0,"ix":4,"mn":"ADBE Vector Group","hd":false}],"ip":0,"op":46.0000018736184,"st":0,"bm":0},{"ddd":0,"ind":26,"ty":4,"nm":"Shape Layer 3","parent":1,"sr":1,"ks":{"o":{"a":1,"k":[{"i":{"x":[0.833],"y":[0.833]},"o":{"x":[0.167],"y":[0.167]},"t":4,"s":[0]},{"i":{"x":[0.833],"y":[0.833]},"o":{"x":[0.167],"y":[0.167]},"t":8,"s":[100]},{"i":{"x":[0.833],"y":[0.833]},"o":{"x":[0.167],"y":[0.167]},"t":420,"s":[100]},{"t":423.000017229143,"s":[0]}],"ix":11},"r":{"a":0,"k":0,"ix":10},"p":{"a":1,"k":[{"i":{"x":0.833,"y":0.833},"o":{"x":0.167,"y":0.167},"t":18,"s":[-128.472,-26.18,0],"to":[0,0,0],"ti":[0,0,0]},{"t":44.0000017921567,"s":[-4.712,-26.18,0]}],"ix":2},"a":{"a":0,"k":[-176.359,67.641,0],"ix":1},"s":{"a":0,"k":[119,119,100],"ix":6}},"ao":0,"shapes":[{"ty":"gr","it":[{"ty":"rc","d":1,"s":{"a":1,"k":[{"i":{"x":[0.833,0.833],"y":[0.833,0.833]},"o":{"x":[0.167,0.167],"y":[0.167,0.167]},"t":18,"s":[455.281,455.281]},{"t":44.0000017921567,"s":[410.281,410.281]}],"ix":2},"p":{"a":0,"k":[0,0],"ix":3},"r":{"a":0,"k":0,"ix":4},"nm":"Rectangle Path 1","mn":"ADBE Vector Shape - Rect","hd":false},{"ty":"st","c":{"a":0,"k":[0,0,0,1],"ix":3},"o":{"a":0,"k":100,"ix":4},"w":{"a":0,"k":6,"ix":5},"lc":1,"lj":1,"ml":4,"bm":0,"nm":"Stroke 1","mn":"ADBE Vector Graphic - Stroke","hd":false},{"ty":"tr","p":{"a":0,"k":[-176.359,67.641],"ix":2},"a":{"a":0,"k":[0,0],"ix":1},"s":{"a":0,"k":[100,100],"ix":3},"r":{"a":0,"k":0,"ix":6},"o":{"a":0,"k":100,"ix":7},"sk":{"a":0,"k":0,"ix":4},"sa":{"a":0,"k":0,"ix":5},"nm":"Transform"}],"nm":"Rectangle 1","np":3,"cix":2,"bm":0,"ix":1,"mn":"ADBE Vector Group","hd":false}],"ip":0,"op":46.0000018736184,"st":0,"bm":0},{"ddd":0,"ind":27,"ty":4,"nm":"Shape Layer 2","parent":1,"sr":1,"ks":{"o":{"a":1,"k":[{"i":{"x":[0.833],"y":[0.833]},"o":{"x":[0.167],"y":[0.167]},"t":4,"s":[0]},{"i":{"x":[0.833],"y":[0.833]},"o":{"x":[0.167],"y":[0.167]},"t":8,"s":[100]},{"i":{"x":[0.833],"y":[0.833]},"o":{"x":[0.167],"y":[0.167]},"t":420,"s":[100]},{"t":423.000017229143,"s":[0]}],"ix":11},"r":{"a":0,"k":0,"ix":10},"p":{"a":1,"k":[{"i":{"x":0.833,"y":0.833},"o":{"x":0.167,"y":0.167},"t":18,"s":[142.42,173.74,0],"to":[0,0,0],"ti":[0,0,0]},{"t":44.0000017921567,"s":[-24.18,173.74,0]}],"ix":2},"a":{"a":0,"k":[-176.359,67.641,0],"ix":1},"s":{"a":0,"k":[119,119,100],"ix":6}},"ao":0,"shapes":[{"ty":"gr","it":[{"ty":"rc","d":1,"s":{"a":1,"k":[{"i":{"x":[0.833,0.833],"y":[0.833,0.833]},"o":{"x":[0.167,0.167],"y":[0.167,0.167]},"t":18,"s":[584.281,584.281]},{"t":44.0000017921567,"s":[531.281,531.281]}],"ix":2},"p":{"a":0,"k":[0,0],"ix":3},"r":{"a":0,"k":0,"ix":4},"nm":"Rectangle Path 1","mn":"ADBE Vector Shape - Rect","hd":false},{"ty":"st","c":{"a":0,"k":[0,0,0,1],"ix":3},"o":{"a":0,"k":100,"ix":4},"w":{"a":0,"k":6,"ix":5},"lc":1,"lj":1,"ml":4,"bm":0,"nm":"Stroke 1","mn":"ADBE Vector Graphic - Stroke","hd":false},{"ty":"tr","p":{"a":0,"k":[-159.547,-82.414],"ix":2},"a":{"a":0,"k":[0,0],"ix":1},"s":{"a":0,"k":[100,100],"ix":3},"r":{"a":0,"k":0,"ix":6},"o":{"a":0,"k":100,"ix":7},"sk":{"a":0,"k":0,"ix":4},"sa":{"a":0,"k":0,"ix":5},"nm":"Transform"}],"nm":"Rectangle 1","np":3,"cix":2,"bm":0,"ix":1,"mn":"ADBE Vector Group","hd":false}],"ip":0,"op":428.000017432797,"st":0,"bm":0}],"markers":[]}